{"url":"http:\/\/localhost:8080\/edit_karyawan\/18","method":"GET","isAJAX":false,"startTime":1694927052.244905,"totalTime":233.8,"totalMemory":"7.823","segmentDuration":35,"segmentCount":7,"CI_VERSION":"4.3.7","collectors":[{"title":"Timers","titleSafe":"timers","titleDetails":"","display":[],"badgeValue":null,"isEmpty":false,"hasTabContent":false,"hasLabel":false,"icon":"","hasTimelineData":true,"timelineData":[{"name":"Bootstrap","component":"Timer","start":1694927052.282164,"duration":0.032182931900024414},{"name":"Routing","component":"Timer","start":1694927052.31435,"duration":0.00039005279541015625},{"name":"Before Filters","component":"Timer","start":1694927052.318163,"duration":0.13999700546264648},{"name":"Controller","component":"Timer","start":1694927052.458166,"duration":0.02055215835571289},{"name":"Controller Constructor","component":"Timer","start":1694927052.458169,"duration":0.003097057342529297},{"name":"After Filters","component":"Timer","start":1694927052.478747,"duration":0.00042510032653808594}]},{"title":"Database","titleSafe":"database","titleDetails":"(9 total Queries, 8 of them unique across 1 Connection)","display":{"queries":[{"hover":"","class":"","duration":"2.47 ms","sql":"<strong>SELECT<\/strong> *\n<strong>FROM<\/strong> &quot;users&quot;\n<strong>WHERE<\/strong> &quot;users&quot;.&quot;deleted_at&quot; <strong>IS<\/strong> <strong>NULL<\/strong>\n<strong>AND<\/strong> &quot;users&quot;.&quot;id&quot; = &#039;1&#039;","trace":[{"file":"SYSTEMPATH\\Database\\BaseBuilder.php:1616","function":"\u00a0\u00a0\u00a0\u00a0\u00a0\u00a0\u00a0\u00a0CodeIgniter\\Database\\BaseConnection->query()","index":"\u00a0\u00a01\u00a0\u00a0\u00a0\u00a0"},{"file":"SYSTEMPATH\\Model.php:200","function":"\u00a0\u00a0\u00a0\u00a0\u00a0\u00a0\u00a0\u00a0CodeIgniter\\Database\\BaseBuilder->get()","index":"\u00a0\u00a02\u00a0\u00a0\u00a0\u00a0"},{"file":"SYSTEMPATH\\BaseModel.php:557","function":"\u00a0\u00a0\u00a0\u00a0\u00a0\u00a0\u00a0\u00a0CodeIgniter\\Model->doFind()","index":"\u00a0\u00a03\u00a0\u00a0\u00a0\u00a0"},{"file":"VENDORPATH\\myth\\auth\\src\\Authentication\\AuthenticationBase.php:130","function":"\u00a0\u00a0\u00a0\u00a0\u00a0\u00a0\u00a0\u00a0CodeIgniter\\BaseModel->find()","index":"\u00a0\u00a04\u00a0\u00a0\u00a0\u00a0"},{"file":"VENDORPATH\\myth\\auth\\src\\Authentication\\LocalAuthenticator.php:67","function":"\u00a0\u00a0\u00a0\u00a0\u00a0\u00a0\u00a0\u00a0Myth\\Auth\\Authentication\\AuthenticationBase->isLoggedIn()","index":"\u00a0\u00a05\u00a0\u00a0\u00a0\u00a0"},{"file":"VENDORPATH\\myth\\auth\\src\\Filters\\LoginFilter.php:29","function":"\u00a0\u00a0\u00a0\u00a0\u00a0\u00a0\u00a0\u00a0Myth\\Auth\\Authentication\\LocalAuthenticator->check()","index":"\u00a0\u00a06\u00a0\u00a0\u00a0\u00a0"},{"file":"SYSTEMPATH\\Filters\\Filters.php:173","function":"\u00a0\u00a0\u00a0\u00a0\u00a0\u00a0\u00a0\u00a0Myth\\Auth\\Filters\\LoginFilter->before()","index":"\u00a0\u00a07\u00a0\u00a0\u00a0\u00a0"},{"file":"SYSTEMPATH\\CodeIgniter.php:471","function":"\u00a0\u00a0\u00a0\u00a0\u00a0\u00a0\u00a0\u00a0CodeIgniter\\Filters\\Filters->run()","index":"\u00a0\u00a08\u00a0\u00a0\u00a0\u00a0"},{"file":"SYSTEMPATH\\CodeIgniter.php:366","function":"\u00a0\u00a0\u00a0\u00a0\u00a0\u00a0\u00a0\u00a0CodeIgniter\\CodeIgniter->handleRequest()","index":"\u00a0\u00a09\u00a0\u00a0\u00a0\u00a0"},{"file":"FCPATH\\index.php:67","function":"\u00a0\u00a0\u00a0\u00a0\u00a0\u00a0\u00a0\u00a0CodeIgniter\\CodeIgniter->run()","index":"\u00a010\u00a0\u00a0\u00a0\u00a0"},{"file":"SYSTEMPATH\\Commands\\Server\\rewrite.php:47","args":["D:\\SKYWORX\\Project\\good-year-new\\GoodYear\\public\\index.php"],"function":"\u00a0\u00a0\u00a0\u00a0\u00a0\u00a0\u00a0\u00a0require_once()","index":"\u00a011\u00a0\u00a0\u00a0\u00a0"}],"trace-file":"VENDORPATH\\myth\\auth\\src\\Authentication\\AuthenticationBase.php:130","qid":"8b53f2d6ffd8eaa102c26016d3b98774"},{"hover":"","class":"","duration":"1.66 ms","sql":"<strong>SELECT<\/strong> *\n<strong>FROM<\/strong> &quot;transaksi_sertifikat&quot;","trace":[{"file":"SYSTEMPATH\\Database\\BaseBuilder.php:1616","function":"\u00a0\u00a0\u00a0\u00a0\u00a0\u00a0\u00a0\u00a0CodeIgniter\\Database\\BaseConnection->query()","index":"\u00a0\u00a01\u00a0\u00a0\u00a0\u00a0"},{"file":"APPPATH\\Models\\TransaksiModel.php:23","function":"\u00a0\u00a0\u00a0\u00a0\u00a0\u00a0\u00a0\u00a0CodeIgniter\\Database\\BaseBuilder->get()","index":"\u00a0\u00a02\u00a0\u00a0\u00a0\u00a0"},{"file":"APPPATH\\Controllers\\DaftarKaryawanController.php:148","function":"\u00a0\u00a0\u00a0\u00a0\u00a0\u00a0\u00a0\u00a0App\\Models\\TransaksiModel->getTransaksi()","index":"\u00a0\u00a03\u00a0\u00a0\u00a0\u00a0"},{"file":"SYSTEMPATH\\CodeIgniter.php:932","function":"\u00a0\u00a0\u00a0\u00a0\u00a0\u00a0\u00a0\u00a0App\\Controllers\\DaftarKaryawanController->edit_karyawan()","index":"\u00a0\u00a04\u00a0\u00a0\u00a0\u00a0"},{"file":"SYSTEMPATH\\CodeIgniter.php:497","function":"\u00a0\u00a0\u00a0\u00a0\u00a0\u00a0\u00a0\u00a0CodeIgniter\\CodeIgniter->runController()","index":"\u00a0\u00a05\u00a0\u00a0\u00a0\u00a0"},{"file":"SYSTEMPATH\\CodeIgniter.php:366","function":"\u00a0\u00a0\u00a0\u00a0\u00a0\u00a0\u00a0\u00a0CodeIgniter\\CodeIgniter->handleRequest()","index":"\u00a0\u00a06\u00a0\u00a0\u00a0\u00a0"},{"file":"FCPATH\\index.php:67","function":"\u00a0\u00a0\u00a0\u00a0\u00a0\u00a0\u00a0\u00a0CodeIgniter\\CodeIgniter->run()","index":"\u00a0\u00a07\u00a0\u00a0\u00a0\u00a0"},{"file":"SYSTEMPATH\\Commands\\Server\\rewrite.php:47","args":["D:\\SKYWORX\\Project\\good-year-new\\GoodYear\\public\\index.php"],"function":"\u00a0\u00a0\u00a0\u00a0\u00a0\u00a0\u00a0\u00a0require_once()","index":"\u00a0\u00a08\u00a0\u00a0\u00a0\u00a0"}],"trace-file":"APPPATH\\Models\\TransaksiModel.php:23","qid":"5cd90160a2c1256766a28bd5f9295a76"},{"hover":"","class":"","duration":"1.66 ms","sql":"<strong>SELECT<\/strong> *\n<strong>FROM<\/strong> &quot;sertifikat&quot;\n<strong>JOIN<\/strong> &quot;transaksi_sertifikat&quot; <strong>ON<\/strong> &quot;transaksi_sertifikat&quot;.&quot;id_sertifikat&quot;=&quot;sertifikat&quot;.&quot;id_sertifikat&quot;","trace":[{"file":"SYSTEMPATH\\Database\\BaseBuilder.php:1616","function":"\u00a0\u00a0\u00a0\u00a0\u00a0\u00a0\u00a0\u00a0CodeIgniter\\Database\\BaseConnection->query()","index":"\u00a0\u00a01\u00a0\u00a0\u00a0\u00a0"},{"file":"APPPATH\\Models\\TransaksiModel.php:30","function":"\u00a0\u00a0\u00a0\u00a0\u00a0\u00a0\u00a0\u00a0CodeIgniter\\Database\\BaseBuilder->get()","index":"\u00a0\u00a02\u00a0\u00a0\u00a0\u00a0"},{"file":"APPPATH\\Controllers\\DaftarKaryawanController.php:149","function":"\u00a0\u00a0\u00a0\u00a0\u00a0\u00a0\u00a0\u00a0App\\Models\\TransaksiModel->getJenisTransaksi()","index":"\u00a0\u00a03\u00a0\u00a0\u00a0\u00a0"},{"file":"SYSTEMPATH\\CodeIgniter.php:932","function":"\u00a0\u00a0\u00a0\u00a0\u00a0\u00a0\u00a0\u00a0App\\Controllers\\DaftarKaryawanController->edit_karyawan()","index":"\u00a0\u00a04\u00a0\u00a0\u00a0\u00a0"},{"file":"SYSTEMPATH\\CodeIgniter.php:497","function":"\u00a0\u00a0\u00a0\u00a0\u00a0\u00a0\u00a0\u00a0CodeIgniter\\CodeIgniter->runController()","index":"\u00a0\u00a05\u00a0\u00a0\u00a0\u00a0"},{"file":"SYSTEMPATH\\CodeIgniter.php:366","function":"\u00a0\u00a0\u00a0\u00a0\u00a0\u00a0\u00a0\u00a0CodeIgniter\\CodeIgniter->handleRequest()","index":"\u00a0\u00a06\u00a0\u00a0\u00a0\u00a0"},{"file":"FCPATH\\index.php:67","function":"\u00a0\u00a0\u00a0\u00a0\u00a0\u00a0\u00a0\u00a0CodeIgniter\\CodeIgniter->run()","index":"\u00a0\u00a07\u00a0\u00a0\u00a0\u00a0"},{"file":"SYSTEMPATH\\Commands\\Server\\rewrite.php:47","args":["D:\\SKYWORX\\Project\\good-year-new\\GoodYear\\public\\index.php"],"function":"\u00a0\u00a0\u00a0\u00a0\u00a0\u00a0\u00a0\u00a0require_once()","index":"\u00a0\u00a08\u00a0\u00a0\u00a0\u00a0"}],"trace-file":"APPPATH\\Models\\TransaksiModel.php:30","qid":"91671da5087814736580965169579143"},{"hover":"","class":"","duration":"0.37 ms","sql":"<strong>SELECT<\/strong> *\n<strong>FROM<\/strong> &quot;sertifikat&quot;\n<strong>JOIN<\/strong> &quot;transaksi_sertifikat&quot; <strong>ON<\/strong> &quot;transaksi_sertifikat&quot;.&quot;id_sertifikat&quot;=&quot;sertifikat&quot;.&quot;id_sertifikat&quot;\n<strong>WHERE<\/strong> &quot;id_karyawan&quot; = &#039;18&#039;","trace":[{"file":"SYSTEMPATH\\Database\\BaseBuilder.php:1616","function":"\u00a0\u00a0\u00a0\u00a0\u00a0\u00a0\u00a0\u00a0CodeIgniter\\Database\\BaseConnection->query()","index":"\u00a0\u00a01\u00a0\u00a0\u00a0\u00a0"},{"file":"APPPATH\\Models\\TransaksiModel.php:38","function":"\u00a0\u00a0\u00a0\u00a0\u00a0\u00a0\u00a0\u00a0CodeIgniter\\Database\\BaseBuilder->get()","index":"\u00a0\u00a02\u00a0\u00a0\u00a0\u00a0"},{"file":"APPPATH\\Controllers\\DaftarKaryawanController.php:150","function":"\u00a0\u00a0\u00a0\u00a0\u00a0\u00a0\u00a0\u00a0App\\Models\\TransaksiModel->getSertifikatPerID()","index":"\u00a0\u00a03\u00a0\u00a0\u00a0\u00a0"},{"file":"SYSTEMPATH\\CodeIgniter.php:932","function":"\u00a0\u00a0\u00a0\u00a0\u00a0\u00a0\u00a0\u00a0App\\Controllers\\DaftarKaryawanController->edit_karyawan()","index":"\u00a0\u00a04\u00a0\u00a0\u00a0\u00a0"},{"file":"SYSTEMPATH\\CodeIgniter.php:497","function":"\u00a0\u00a0\u00a0\u00a0\u00a0\u00a0\u00a0\u00a0CodeIgniter\\CodeIgniter->runController()","index":"\u00a0\u00a05\u00a0\u00a0\u00a0\u00a0"},{"file":"SYSTEMPATH\\CodeIgniter.php:366","function":"\u00a0\u00a0\u00a0\u00a0\u00a0\u00a0\u00a0\u00a0CodeIgniter\\CodeIgniter->handleRequest()","index":"\u00a0\u00a06\u00a0\u00a0\u00a0\u00a0"},{"file":"FCPATH\\index.php:67","function":"\u00a0\u00a0\u00a0\u00a0\u00a0\u00a0\u00a0\u00a0CodeIgniter\\CodeIgniter->run()","index":"\u00a0\u00a07\u00a0\u00a0\u00a0\u00a0"},{"file":"SYSTEMPATH\\Commands\\Server\\rewrite.php:47","args":["D:\\SKYWORX\\Project\\good-year-new\\GoodYear\\public\\index.php"],"function":"\u00a0\u00a0\u00a0\u00a0\u00a0\u00a0\u00a0\u00a0require_once()","index":"\u00a0\u00a08\u00a0\u00a0\u00a0\u00a0"}],"trace-file":"APPPATH\\Models\\TransaksiModel.php:38","qid":"90e40554613679738833cfde38db6539"},{"hover":"","class":"","duration":"0.22 ms","sql":"<strong>SELECT<\/strong> *\n<strong>FROM<\/strong> &quot;sertifikat&quot;","trace":[{"file":"SYSTEMPATH\\Database\\BaseBuilder.php:1616","function":"\u00a0\u00a0\u00a0\u00a0\u00a0\u00a0\u00a0\u00a0CodeIgniter\\Database\\BaseConnection->query()","index":"\u00a0\u00a01\u00a0\u00a0\u00a0\u00a0"},{"file":"APPPATH\\Models\\DaftarSertifikatModel.php:21","function":"\u00a0\u00a0\u00a0\u00a0\u00a0\u00a0\u00a0\u00a0CodeIgniter\\Database\\BaseBuilder->get()","index":"\u00a0\u00a02\u00a0\u00a0\u00a0\u00a0"},{"file":"APPPATH\\Controllers\\DaftarKaryawanController.php:151","function":"\u00a0\u00a0\u00a0\u00a0\u00a0\u00a0\u00a0\u00a0App\\Models\\DaftarSertifikatModel->getJenisSertifikat()","index":"\u00a0\u00a03\u00a0\u00a0\u00a0\u00a0"},{"file":"SYSTEMPATH\\CodeIgniter.php:932","function":"\u00a0\u00a0\u00a0\u00a0\u00a0\u00a0\u00a0\u00a0App\\Controllers\\DaftarKaryawanController->edit_karyawan()","index":"\u00a0\u00a04\u00a0\u00a0\u00a0\u00a0"},{"file":"SYSTEMPATH\\CodeIgniter.php:497","function":"\u00a0\u00a0\u00a0\u00a0\u00a0\u00a0\u00a0\u00a0CodeIgniter\\CodeIgniter->runController()","index":"\u00a0\u00a05\u00a0\u00a0\u00a0\u00a0"},{"file":"SYSTEMPATH\\CodeIgniter.php:366","function":"\u00a0\u00a0\u00a0\u00a0\u00a0\u00a0\u00a0\u00a0CodeIgniter\\CodeIgniter->handleRequest()","index":"\u00a0\u00a06\u00a0\u00a0\u00a0\u00a0"},{"file":"FCPATH\\index.php:67","function":"\u00a0\u00a0\u00a0\u00a0\u00a0\u00a0\u00a0\u00a0CodeIgniter\\CodeIgniter->run()","index":"\u00a0\u00a07\u00a0\u00a0\u00a0\u00a0"},{"file":"SYSTEMPATH\\Commands\\Server\\rewrite.php:47","args":["D:\\SKYWORX\\Project\\good-year-new\\GoodYear\\public\\index.php"],"function":"\u00a0\u00a0\u00a0\u00a0\u00a0\u00a0\u00a0\u00a0require_once()","index":"\u00a0\u00a08\u00a0\u00a0\u00a0\u00a0"}],"trace-file":"APPPATH\\Models\\DaftarSertifikatModel.php:21","qid":"0cd5afa2e8773d3f99a170fc3258f7cd"},{"hover":"This query was called more than once.","class":"duplicate","duration":"0.24 ms","sql":"<strong>SELECT<\/strong> *\n<strong>FROM<\/strong> &quot;sertifikat&quot;","trace":[{"file":"SYSTEMPATH\\Database\\BaseBuilder.php:1616","function":"\u00a0\u00a0\u00a0\u00a0\u00a0\u00a0\u00a0\u00a0CodeIgniter\\Database\\BaseConnection->query()","index":"\u00a0\u00a01\u00a0\u00a0\u00a0\u00a0"},{"file":"APPPATH\\Models\\DaftarSertifikatModel.php:21","function":"\u00a0\u00a0\u00a0\u00a0\u00a0\u00a0\u00a0\u00a0CodeIgniter\\Database\\BaseBuilder->get()","index":"\u00a0\u00a02\u00a0\u00a0\u00a0\u00a0"},{"file":"APPPATH\\Controllers\\DaftarKaryawanController.php:152","function":"\u00a0\u00a0\u00a0\u00a0\u00a0\u00a0\u00a0\u00a0App\\Models\\DaftarSertifikatModel->getJenisSertifikat()","index":"\u00a0\u00a03\u00a0\u00a0\u00a0\u00a0"},{"file":"SYSTEMPATH\\CodeIgniter.php:932","function":"\u00a0\u00a0\u00a0\u00a0\u00a0\u00a0\u00a0\u00a0App\\Controllers\\DaftarKaryawanController->edit_karyawan()","index":"\u00a0\u00a04\u00a0\u00a0\u00a0\u00a0"},{"file":"SYSTEMPATH\\CodeIgniter.php:497","function":"\u00a0\u00a0\u00a0\u00a0\u00a0\u00a0\u00a0\u00a0CodeIgniter\\CodeIgniter->runController()","index":"\u00a0\u00a05\u00a0\u00a0\u00a0\u00a0"},{"file":"SYSTEMPATH\\CodeIgniter.php:366","function":"\u00a0\u00a0\u00a0\u00a0\u00a0\u00a0\u00a0\u00a0CodeIgniter\\CodeIgniter->handleRequest()","index":"\u00a0\u00a06\u00a0\u00a0\u00a0\u00a0"},{"file":"FCPATH\\index.php:67","function":"\u00a0\u00a0\u00a0\u00a0\u00a0\u00a0\u00a0\u00a0CodeIgniter\\CodeIgniter->run()","index":"\u00a0\u00a07\u00a0\u00a0\u00a0\u00a0"},{"file":"SYSTEMPATH\\Commands\\Server\\rewrite.php:47","args":["D:\\SKYWORX\\Project\\good-year-new\\GoodYear\\public\\index.php"],"function":"\u00a0\u00a0\u00a0\u00a0\u00a0\u00a0\u00a0\u00a0require_once()","index":"\u00a0\u00a08\u00a0\u00a0\u00a0\u00a0"}],"trace-file":"APPPATH\\Models\\DaftarSertifikatModel.php:21","qid":"7a7f7824de9e3486e84e2f33816bacc6"},{"hover":"","class":"","duration":"2.59 ms","sql":"<strong>SELECT<\/strong> *\n<strong>FROM<\/strong> &quot;karyawan&quot;\n<strong>WHERE<\/strong> &quot;karyawan&quot;.&quot;id_karyawan&quot; = &#039;18&#039;","trace":[{"file":"SYSTEMPATH\\Database\\BaseBuilder.php:1616","function":"\u00a0\u00a0\u00a0\u00a0\u00a0\u00a0\u00a0\u00a0CodeIgniter\\Database\\BaseConnection->query()","index":"\u00a0\u00a01\u00a0\u00a0\u00a0\u00a0"},{"file":"SYSTEMPATH\\Model.php:200","function":"\u00a0\u00a0\u00a0\u00a0\u00a0\u00a0\u00a0\u00a0CodeIgniter\\Database\\BaseBuilder->get()","index":"\u00a0\u00a02\u00a0\u00a0\u00a0\u00a0"},{"file":"SYSTEMPATH\\BaseModel.php:557","function":"\u00a0\u00a0\u00a0\u00a0\u00a0\u00a0\u00a0\u00a0CodeIgniter\\Model->doFind()","index":"\u00a0\u00a03\u00a0\u00a0\u00a0\u00a0"},{"file":"APPPATH\\Controllers\\DaftarKaryawanController.php:153","function":"\u00a0\u00a0\u00a0\u00a0\u00a0\u00a0\u00a0\u00a0CodeIgniter\\BaseModel->find()","index":"\u00a0\u00a04\u00a0\u00a0\u00a0\u00a0"},{"file":"SYSTEMPATH\\CodeIgniter.php:932","function":"\u00a0\u00a0\u00a0\u00a0\u00a0\u00a0\u00a0\u00a0App\\Controllers\\DaftarKaryawanController->edit_karyawan()","index":"\u00a0\u00a05\u00a0\u00a0\u00a0\u00a0"},{"file":"SYSTEMPATH\\CodeIgniter.php:497","function":"\u00a0\u00a0\u00a0\u00a0\u00a0\u00a0\u00a0\u00a0CodeIgniter\\CodeIgniter->runController()","index":"\u00a0\u00a06\u00a0\u00a0\u00a0\u00a0"},{"file":"SYSTEMPATH\\CodeIgniter.php:366","function":"\u00a0\u00a0\u00a0\u00a0\u00a0\u00a0\u00a0\u00a0CodeIgniter\\CodeIgniter->handleRequest()","index":"\u00a0\u00a07\u00a0\u00a0\u00a0\u00a0"},{"file":"FCPATH\\index.php:67","function":"\u00a0\u00a0\u00a0\u00a0\u00a0\u00a0\u00a0\u00a0CodeIgniter\\CodeIgniter->run()","index":"\u00a0\u00a08\u00a0\u00a0\u00a0\u00a0"},{"file":"SYSTEMPATH\\Commands\\Server\\rewrite.php:47","args":["D:\\SKYWORX\\Project\\good-year-new\\GoodYear\\public\\index.php"],"function":"\u00a0\u00a0\u00a0\u00a0\u00a0\u00a0\u00a0\u00a0require_once()","index":"\u00a0\u00a09\u00a0\u00a0\u00a0\u00a0"}],"trace-file":"APPPATH\\Controllers\\DaftarKaryawanController.php:153","qid":"1c6896bd2a7849e6cf6a9e9259e121ce"},{"hover":"","class":"","duration":"2.6 ms","sql":"<strong>SELECT<\/strong> *\n<strong>FROM<\/strong> &quot;jabatan&quot;","trace":[{"file":"SYSTEMPATH\\Database\\BaseBuilder.php:1616","function":"\u00a0\u00a0\u00a0\u00a0\u00a0\u00a0\u00a0\u00a0CodeIgniter\\Database\\BaseConnection->query()","index":"\u00a0\u00a01\u00a0\u00a0\u00a0\u00a0"},{"file":"SYSTEMPATH\\Model.php:241","function":"\u00a0\u00a0\u00a0\u00a0\u00a0\u00a0\u00a0\u00a0CodeIgniter\\Database\\BaseBuilder->get()","index":"\u00a0\u00a02\u00a0\u00a0\u00a0\u00a0"},{"file":"SYSTEMPATH\\BaseModel.php:618","function":"\u00a0\u00a0\u00a0\u00a0\u00a0\u00a0\u00a0\u00a0CodeIgniter\\Model->doFindAll()","index":"\u00a0\u00a03\u00a0\u00a0\u00a0\u00a0"},{"file":"APPPATH\\Controllers\\DaftarKaryawanController.php:154","function":"\u00a0\u00a0\u00a0\u00a0\u00a0\u00a0\u00a0\u00a0CodeIgniter\\BaseModel->findAll()","index":"\u00a0\u00a04\u00a0\u00a0\u00a0\u00a0"},{"file":"SYSTEMPATH\\CodeIgniter.php:932","function":"\u00a0\u00a0\u00a0\u00a0\u00a0\u00a0\u00a0\u00a0App\\Controllers\\DaftarKaryawanController->edit_karyawan()","index":"\u00a0\u00a05\u00a0\u00a0\u00a0\u00a0"},{"file":"SYSTEMPATH\\CodeIgniter.php:497","function":"\u00a0\u00a0\u00a0\u00a0\u00a0\u00a0\u00a0\u00a0CodeIgniter\\CodeIgniter->runController()","index":"\u00a0\u00a06\u00a0\u00a0\u00a0\u00a0"},{"file":"SYSTEMPATH\\CodeIgniter.php:366","function":"\u00a0\u00a0\u00a0\u00a0\u00a0\u00a0\u00a0\u00a0CodeIgniter\\CodeIgniter->handleRequest()","index":"\u00a0\u00a07\u00a0\u00a0\u00a0\u00a0"},{"file":"FCPATH\\index.php:67","function":"\u00a0\u00a0\u00a0\u00a0\u00a0\u00a0\u00a0\u00a0CodeIgniter\\CodeIgniter->run()","index":"\u00a0\u00a08\u00a0\u00a0\u00a0\u00a0"},{"file":"SYSTEMPATH\\Commands\\Server\\rewrite.php:47","args":["D:\\SKYWORX\\Project\\good-year-new\\GoodYear\\public\\index.php"],"function":"\u00a0\u00a0\u00a0\u00a0\u00a0\u00a0\u00a0\u00a0require_once()","index":"\u00a0\u00a09\u00a0\u00a0\u00a0\u00a0"}],"trace-file":"APPPATH\\Controllers\\DaftarKaryawanController.php:154","qid":"a7f1485e659c4f2822218001f3c4d563"},{"hover":"","class":"","duration":"1.68 ms","sql":"<strong>SELECT<\/strong> *\n<strong>FROM<\/strong> &quot;divisi&quot;","trace":[{"file":"SYSTEMPATH\\Database\\BaseBuilder.php:1616","function":"\u00a0\u00a0\u00a0\u00a0\u00a0\u00a0\u00a0\u00a0CodeIgniter\\Database\\BaseConnection->query()","index":"\u00a0\u00a01\u00a0\u00a0\u00a0\u00a0"},{"file":"SYSTEMPATH\\Model.php:241","function":"\u00a0\u00a0\u00a0\u00a0\u00a0\u00a0\u00a0\u00a0CodeIgniter\\Database\\BaseBuilder->get()","index":"\u00a0\u00a02\u00a0\u00a0\u00a0\u00a0"},{"file":"SYSTEMPATH\\BaseModel.php:618","function":"\u00a0\u00a0\u00a0\u00a0\u00a0\u00a0\u00a0\u00a0CodeIgniter\\Model->doFindAll()","index":"\u00a0\u00a03\u00a0\u00a0\u00a0\u00a0"},{"file":"APPPATH\\Controllers\\DaftarKaryawanController.php:155","function":"\u00a0\u00a0\u00a0\u00a0\u00a0\u00a0\u00a0\u00a0CodeIgniter\\BaseModel->findAll()","index":"\u00a0\u00a04\u00a0\u00a0\u00a0\u00a0"},{"file":"SYSTEMPATH\\CodeIgniter.php:932","function":"\u00a0\u00a0\u00a0\u00a0\u00a0\u00a0\u00a0\u00a0App\\Controllers\\DaftarKaryawanController->edit_karyawan()","index":"\u00a0\u00a05\u00a0\u00a0\u00a0\u00a0"},{"file":"SYSTEMPATH\\CodeIgniter.php:497","function":"\u00a0\u00a0\u00a0\u00a0\u00a0\u00a0\u00a0\u00a0CodeIgniter\\CodeIgniter->runController()","index":"\u00a0\u00a06\u00a0\u00a0\u00a0\u00a0"},{"file":"SYSTEMPATH\\CodeIgniter.php:366","function":"\u00a0\u00a0\u00a0\u00a0\u00a0\u00a0\u00a0\u00a0CodeIgniter\\CodeIgniter->handleRequest()","index":"\u00a0\u00a07\u00a0\u00a0\u00a0\u00a0"},{"file":"FCPATH\\index.php:67","function":"\u00a0\u00a0\u00a0\u00a0\u00a0\u00a0\u00a0\u00a0CodeIgniter\\CodeIgniter->run()","index":"\u00a0\u00a08\u00a0\u00a0\u00a0\u00a0"},{"file":"SYSTEMPATH\\Commands\\Server\\rewrite.php:47","args":["D:\\SKYWORX\\Project\\good-year-new\\GoodYear\\public\\index.php"],"function":"\u00a0\u00a0\u00a0\u00a0\u00a0\u00a0\u00a0\u00a0require_once()","index":"\u00a0\u00a09\u00a0\u00a0\u00a0\u00a0"}],"trace-file":"APPPATH\\Controllers\\DaftarKaryawanController.php:155","qid":"7a32f8818b1f842a0149db363f86ef7d"}]},"badgeValue":9,"isEmpty":false,"hasTabContent":true,"hasLabel":false,"icon":"data:image\/png;base64,iVBORw0KGgoAAAANSUhEUgAAABgAAAAYCAYAAADgdz34AAAAAXNSR0IArs4c6QAAAARnQU1BAACxjwv8YQUAAAAJcEhZcwAADsMAAA7DAcdvqGQAAADMSURBVEhLY6A3YExLSwsA4nIycQDIDIhRWEBqamo\/UNF\/SjDQjF6ocZgAKPkRiFeEhoYyQ4WIBiA9QAuWAPEHqBAmgLqgHcolGQD1V4DMgHIxwbCxYD+QBqcKINseKo6eWrBioPrtQBq\/BcgY5ht0cUIYbBg2AJKkRxCNWkDQgtFUNJwtABr+F6igE8olGQD114HMgHIxAVDyAhA\/AlpSA8RYUwoeXAPVex5qHCbIyMgwBCkAuQJIY00huDBUz\/mUlBQDqHGjgBjAwAAACexpph6oHSQAAAAASUVORK5CYII=","hasTimelineData":true,"timelineData":[{"name":"Connecting to Database: \"default\"","component":"Database","start":1694927052.378932,"duration":"0.067819"},{"name":"Query","component":"Database","start":1694927052.448427,"duration":"0.002468","query":"<strong>SELECT<\/strong> *\n<strong>FROM<\/strong> &quot;users&quot;\n<strong>WHERE<\/strong> &quot;users&quot;.&quot;deleted_at&quot; <strong>IS<\/strong> <strong>NULL<\/strong>\n<strong>AND<\/strong> &quot;users&quot;.&quot;id&quot; = &#039;1&#039;"},{"name":"Query","component":"Database","start":1694927052.46133,"duration":"0.001663","query":"<strong>SELECT<\/strong> *\n<strong>FROM<\/strong> &quot;transaksi_sertifikat&quot;"},{"name":"Query","component":"Database","start":1694927052.463248,"duration":"0.001662","query":"<strong>SELECT<\/strong> *\n<strong>FROM<\/strong> &quot;sertifikat&quot;\n<strong>JOIN<\/strong> &quot;transaksi_sertifikat&quot; <strong>ON<\/strong> &quot;transaksi_sertifikat&quot;.&quot;id_sertifikat&quot;=&quot;sertifikat&quot;.&quot;id_sertifikat&quot;"},{"name":"Query","component":"Database","start":1694927052.465141,"duration":"0.000372","query":"<strong>SELECT<\/strong> *\n<strong>FROM<\/strong> &quot;sertifikat&quot;\n<strong>JOIN<\/strong> &quot;transaksi_sertifikat&quot; <strong>ON<\/strong> &quot;transaksi_sertifikat&quot;.&quot;id_sertifikat&quot;=&quot;sertifikat&quot;.&quot;id_sertifikat&quot;\n<strong>WHERE<\/strong> &quot;id_karyawan&quot; = &#039;18&#039;"},{"name":"Query","component":"Database","start":1694927052.465636,"duration":"0.000222","query":"<strong>SELECT<\/strong> *\n<strong>FROM<\/strong> &quot;sertifikat&quot;"},{"name":"Query","component":"Database","start":1694927052.465961,"duration":"0.000236","query":"<strong>SELECT<\/strong> *\n<strong>FROM<\/strong> &quot;sertifikat&quot;"},{"name":"Query","component":"Database","start":1694927052.466376,"duration":"0.002592","query":"<strong>SELECT<\/strong> *\n<strong>FROM<\/strong> &quot;karyawan&quot;\n<strong>WHERE<\/strong> &quot;karyawan&quot;.&quot;id_karyawan&quot; = &#039;18&#039;"},{"name":"Query","component":"Database","start":1694927052.469163,"duration":"0.002598","query":"<strong>SELECT<\/strong> *\n<strong>FROM<\/strong> &quot;jabatan&quot;"},{"name":"Query","component":"Database","start":1694927052.471969,"duration":"0.001676","query":"<strong>SELECT<\/strong> *\n<strong>FROM<\/strong> &quot;divisi&quot;"}]},{"title":"Logs","titleSafe":"logs","titleDetails":"","display":{"logs":[{"level":"info","msg":"Session: Class initialized using 'CodeIgniter\\Session\\Handlers\\FileHandler' driver."}]},"badgeValue":null,"isEmpty":false,"hasTabContent":true,"hasLabel":false,"icon":"data:image\/png;base64,iVBORw0KGgoAAAANSUhEUgAAABgAAAAYCAYAAADgdz34AAAAAXNSR0IArs4c6QAAAARnQU1BAACxjwv8YQUAAAAJcEhZcwAADsMAAA7DAcdvqGQAAACYSURBVEhLYxgFJIHU1FSjtLS0i0D8AYj7gEKMEBkqAaAFF4D4ERCvAFrwH4gDoFIMKSkpFkB+OTEYqgUTACXfA\/GqjIwMQyD9H2hRHlQKJFcBEiMGQ7VgAqCBvUgK32dmZspCpagGGNPT0\/1BLqeF4bQHQJePpiIwhmrBBEADR1MRfgB0+WgqAmOoFkwANHA0FY0CUgEDAwCQ0PUpNB3kqwAAAABJRU5ErkJggg==","hasTimelineData":false,"timelineData":[]},{"title":"Views","titleSafe":"views","titleDetails":"","display":[],"badgeValue":1,"isEmpty":false,"hasTabContent":false,"hasLabel":true,"icon":"data:image\/png;base64,iVBORw0KGgoAAAANSUhEUgAAABgAAAAYCAYAAADgdz34AAAAAXNSR0IArs4c6QAAAARnQU1BAACxjwv8YQUAAAAJcEhZcwAADsMAAA7DAcdvqGQAAADeSURBVEhL7ZSxDcIwEEWNYA0YgGmgyAaJLTcUaaBzQQEVjMEabBQxAdw53zTHiThEovGTfnE\/9rsoRUxhKLOmaa6Uh7X2+UvguLCzVxN1XW9x4EYHzik033Hp3X0LO+DaQG8MDQcuq6qao4qkHuMgQggLvkPLjqh00ZgFDBacMJYFkuwFlH1mshdkZ5JPJERA9JpI6xNCBESvibQ+IURA9JpI6xNCBESvibQ+IURA9DTsuHTOrVFFxixgB\/eUFlU8uKJ0eDBFOu\/9EvoeKnlJS2\/08Tc8NOwQ8sIfMeYFjqKDjdU2sp4AAAAASUVORK5CYII=","hasTimelineData":true,"timelineData":[{"name":"View: edit_karyawan.php","component":"Views","start":1694927052.473836,"duration":0.004769086837768555}]},{"title":"Files","titleSafe":"files","titleDetails":"( 196 )","display":{"coreFiles":[{"name":"AutoloadConfig.php","path":"SYSTEMPATH\\Config\\AutoloadConfig.php"},{"name":"Autoloader.php","path":"SYSTEMPATH\\Autoloader\\Autoloader.php"},{"name":"BaseBuilder.php","path":"SYSTEMPATH\\Database\\BaseBuilder.php"},{"name":"BaseCast.php","path":"SYSTEMPATH\\Entity\\Cast\\BaseCast.php"},{"name":"BaseCollector.php","path":"SYSTEMPATH\\Debug\\Toolbar\\Collectors\\BaseCollector.php"},{"name":"BaseConfig.php","path":"SYSTEMPATH\\Config\\BaseConfig.php"},{"name":"BaseConnection.php","path":"SYSTEMPATH\\Database\\BaseConnection.php"},{"name":"BaseHandler.php","path":"SYSTEMPATH\\Cache\\Handlers\\BaseHandler.php"},{"name":"BaseHandler.php","path":"SYSTEMPATH\\Log\\Handlers\\BaseHandler.php"},{"name":"BaseHandler.php","path":"SYSTEMPATH\\Session\\Handlers\\BaseHandler.php"},{"name":"BaseModel.php","path":"SYSTEMPATH\\BaseModel.php"},{"name":"BaseResult.php","path":"SYSTEMPATH\\Database\\BaseResult.php"},{"name":"BaseService.php","path":"SYSTEMPATH\\Config\\BaseService.php"},{"name":"BooleanCast.php","path":"SYSTEMPATH\\Entity\\Cast\\BooleanCast.php"},{"name":"Builder.php","path":"SYSTEMPATH\\Database\\Postgre\\Builder.php"},{"name":"CacheFactory.php","path":"SYSTEMPATH\\Cache\\CacheFactory.php"},{"name":"CacheInterface.php","path":"SYSTEMPATH\\Cache\\CacheInterface.php"},{"name":"CastInterface.php","path":"SYSTEMPATH\\Entity\\Cast\\CastInterface.php"},{"name":"CloneableCookieInterface.php","path":"SYSTEMPATH\\Cookie\\CloneableCookieInterface.php"},{"name":"CodeIgniter.php","path":"SYSTEMPATH\\CodeIgniter.php"},{"name":"Common.php","path":"SYSTEMPATH\\Common.php"},{"name":"ConditionalTrait.php","path":"SYSTEMPATH\\Traits\\ConditionalTrait.php"},{"name":"Config.php","path":"SYSTEMPATH\\Database\\Config.php"},{"name":"Connection.php","path":"SYSTEMPATH\\Database\\Postgre\\Connection.php"},{"name":"ConnectionInterface.php","path":"SYSTEMPATH\\Database\\ConnectionInterface.php"},{"name":"ContentSecurityPolicy.php","path":"SYSTEMPATH\\HTTP\\ContentSecurityPolicy.php"},{"name":"Controller.php","path":"SYSTEMPATH\\Controller.php"},{"name":"Cookie.php","path":"SYSTEMPATH\\Cookie\\Cookie.php"},{"name":"CookieInterface.php","path":"SYSTEMPATH\\Cookie\\CookieInterface.php"},{"name":"CookieStore.php","path":"SYSTEMPATH\\Cookie\\CookieStore.php"},{"name":"Database.php","path":"SYSTEMPATH\\Database\\Database.php"},{"name":"Database.php","path":"SYSTEMPATH\\Debug\\Toolbar\\Collectors\\Database.php"},{"name":"DebugToolbar.php","path":"SYSTEMPATH\\Filters\\DebugToolbar.php"},{"name":"DotEnv.php","path":"SYSTEMPATH\\Config\\DotEnv.php"},{"name":"Entity.php","path":"SYSTEMPATH\\Entity\\Entity.php"},{"name":"Events.php","path":"SYSTEMPATH\\Debug\\Toolbar\\Collectors\\Events.php"},{"name":"Events.php","path":"SYSTEMPATH\\Events\\Events.php"},{"name":"Exceptions.php","path":"SYSTEMPATH\\Debug\\Exceptions.php"},{"name":"Factories.php","path":"SYSTEMPATH\\Config\\Factories.php"},{"name":"Factory.php","path":"SYSTEMPATH\\Config\\Factory.php"},{"name":"FileHandler.php","path":"SYSTEMPATH\\Cache\\Handlers\\FileHandler.php"},{"name":"FileHandler.php","path":"SYSTEMPATH\\Log\\Handlers\\FileHandler.php"},{"name":"FileHandler.php","path":"SYSTEMPATH\\Session\\Handlers\\FileHandler.php"},{"name":"FileLocator.php","path":"SYSTEMPATH\\Autoloader\\FileLocator.php"},{"name":"Files.php","path":"SYSTEMPATH\\Debug\\Toolbar\\Collectors\\Files.php"},{"name":"FilterInterface.php","path":"SYSTEMPATH\\Filters\\FilterInterface.php"},{"name":"Filters.php","path":"SYSTEMPATH\\Filters\\Filters.php"},{"name":"FormatRules.php","path":"SYSTEMPATH\\Validation\\FormatRules.php"},{"name":"HandlerInterface.php","path":"SYSTEMPATH\\Log\\Handlers\\HandlerInterface.php"},{"name":"Header.php","path":"SYSTEMPATH\\HTTP\\Header.php"},{"name":"IncomingRequest.php","path":"SYSTEMPATH\\HTTP\\IncomingRequest.php"},{"name":"Logger.php","path":"SYSTEMPATH\\Log\\Logger.php"},{"name":"Logs.php","path":"SYSTEMPATH\\Debug\\Toolbar\\Collectors\\Logs.php"},{"name":"Message.php","path":"SYSTEMPATH\\HTTP\\Message.php"},{"name":"MessageInterface.php","path":"SYSTEMPATH\\HTTP\\MessageInterface.php"},{"name":"MessageTrait.php","path":"SYSTEMPATH\\HTTP\\MessageTrait.php"},{"name":"Model.php","path":"SYSTEMPATH\\Model.php"},{"name":"Modules.php","path":"SYSTEMPATH\\Modules\\Modules.php"},{"name":"OutgoingRequest.php","path":"SYSTEMPATH\\HTTP\\OutgoingRequest.php"},{"name":"OutgoingRequestInterface.php","path":"SYSTEMPATH\\HTTP\\OutgoingRequestInterface.php"},{"name":"Query.php","path":"SYSTEMPATH\\Database\\Query.php"},{"name":"QueryInterface.php","path":"SYSTEMPATH\\Database\\QueryInterface.php"},{"name":"RendererInterface.php","path":"SYSTEMPATH\\View\\RendererInterface.php"},{"name":"Request.php","path":"SYSTEMPATH\\HTTP\\Request.php"},{"name":"RequestInterface.php","path":"SYSTEMPATH\\HTTP\\RequestInterface.php"},{"name":"RequestTrait.php","path":"SYSTEMPATH\\HTTP\\RequestTrait.php"},{"name":"Response.php","path":"SYSTEMPATH\\HTTP\\Response.php"},{"name":"ResponseInterface.php","path":"SYSTEMPATH\\HTTP\\ResponseInterface.php"},{"name":"ResponseTrait.php","path":"SYSTEMPATH\\API\\ResponseTrait.php"},{"name":"ResponseTrait.php","path":"SYSTEMPATH\\HTTP\\ResponseTrait.php"},{"name":"Result.php","path":"SYSTEMPATH\\Database\\Postgre\\Result.php"},{"name":"ResultInterface.php","path":"SYSTEMPATH\\Database\\ResultInterface.php"},{"name":"RouteCollection.php","path":"SYSTEMPATH\\Router\\RouteCollection.php"},{"name":"RouteCollectionInterface.php","path":"SYSTEMPATH\\Router\\RouteCollectionInterface.php"},{"name":"Router.php","path":"SYSTEMPATH\\Router\\Router.php"},{"name":"RouterInterface.php","path":"SYSTEMPATH\\Router\\RouterInterface.php"},{"name":"Routes.php","path":"SYSTEMPATH\\Debug\\Toolbar\\Collectors\\Routes.php"},{"name":"Security.php","path":"SYSTEMPATH\\Security\\Security.php"},{"name":"SecurityInterface.php","path":"SYSTEMPATH\\Security\\SecurityInterface.php"},{"name":"Services.php","path":"SYSTEMPATH\\Config\\Services.php"},{"name":"Session.php","path":"SYSTEMPATH\\Session\\Session.php"},{"name":"SessionInterface.php","path":"SYSTEMPATH\\Session\\SessionInterface.php"},{"name":"Time.php","path":"SYSTEMPATH\\I18n\\Time.php"},{"name":"TimeTrait.php","path":"SYSTEMPATH\\I18n\\TimeTrait.php"},{"name":"Timer.php","path":"SYSTEMPATH\\Debug\\Timer.php"},{"name":"Timers.php","path":"SYSTEMPATH\\Debug\\Toolbar\\Collectors\\Timers.php"},{"name":"Toolbar.php","path":"SYSTEMPATH\\Debug\\Toolbar.php"},{"name":"URI.php","path":"SYSTEMPATH\\HTTP\\URI.php"},{"name":"UserAgent.php","path":"SYSTEMPATH\\HTTP\\UserAgent.php"},{"name":"Validation.php","path":"SYSTEMPATH\\Validation\\Validation.php"},{"name":"ValidationInterface.php","path":"SYSTEMPATH\\Validation\\ValidationInterface.php"},{"name":"View.php","path":"SYSTEMPATH\\Config\\View.php"},{"name":"View.php","path":"SYSTEMPATH\\View\\View.php"},{"name":"ViewDecoratorTrait.php","path":"SYSTEMPATH\\View\\ViewDecoratorTrait.php"},{"name":"Views.php","path":"SYSTEMPATH\\Debug\\Toolbar\\Collectors\\Views.php"},{"name":"array_helper.php","path":"SYSTEMPATH\\Helpers\\array_helper.php"},{"name":"bootstrap.php","path":"SYSTEMPATH\\bootstrap.php"},{"name":"kint_helper.php","path":"SYSTEMPATH\\Helpers\\kint_helper.php"},{"name":"rewrite.php","path":"SYSTEMPATH\\Commands\\Server\\rewrite.php"},{"name":"url_helper.php","path":"SYSTEMPATH\\Helpers\\url_helper.php"}],"userFiles":[{"name":"AbstractRenderer.php","path":"VENDORPATH\\kint-php\\kint\\src\\Renderer\\AbstractRenderer.php"},{"name":"App.php","path":"APPPATH\\Config\\App.php"},{"name":"Auth.php","path":"APPPATH\\Config\\Auth.php"},{"name":"Auth.php","path":"VENDORPATH\\myth\\auth\\src\\Config\\Auth.php"},{"name":"AuthenticationBase.php","path":"VENDORPATH\\myth\\auth\\src\\Authentication\\AuthenticationBase.php"},{"name":"AuthenticatorInterface.php","path":"VENDORPATH\\myth\\auth\\src\\Authentication\\AuthenticatorInterface.php"},{"name":"AuthorizeInterface.php","path":"VENDORPATH\\myth\\auth\\src\\Authorization\\AuthorizeInterface.php"},{"name":"Autoload.php","path":"APPPATH\\Config\\Autoload.php"},{"name":"BaseController.php","path":"APPPATH\\Controllers\\BaseController.php"},{"name":"BaseFilter.php","path":"VENDORPATH\\myth\\auth\\src\\Filters\\BaseFilter.php"},{"name":"Cache.php","path":"APPPATH\\Config\\Cache.php"},{"name":"ClassLoader.php","path":"VENDORPATH\\composer\\ClassLoader.php"},{"name":"CliRenderer.php","path":"VENDORPATH\\kint-php\\kint\\src\\Renderer\\CliRenderer.php"},{"name":"Common.php","path":"APPPATH\\Common.php"},{"name":"Constants.php","path":"APPPATH\\Config\\Constants.php"},{"name":"ContentSecurityPolicy.php","path":"APPPATH\\Config\\ContentSecurityPolicy.php"},{"name":"Cookie.php","path":"APPPATH\\Config\\Cookie.php"},{"name":"DaftarDivisiModel.php","path":"APPPATH\\Models\\DaftarDivisiModel.php"},{"name":"DaftarJabatanModel.php","path":"APPPATH\\Models\\DaftarJabatanModel.php"},{"name":"DaftarKaryawanController.php","path":"APPPATH\\Controllers\\DaftarKaryawanController.php"},{"name":"DaftarKaryawanModel.php","path":"APPPATH\\Models\\DaftarKaryawanModel.php"},{"name":"DaftarSertifikatModel.php","path":"APPPATH\\Models\\DaftarSertifikatModel.php"},{"name":"Database.php","path":"APPPATH\\Config\\Database.php"},{"name":"DocTypes.php","path":"APPPATH\\Config\\DocTypes.php"},{"name":"Escaper.php","path":"VENDORPATH\\laminas\\laminas-escaper\\src\\Escaper.php"},{"name":"Events.php","path":"APPPATH\\Config\\Events.php"},{"name":"Exceptions.php","path":"APPPATH\\Config\\Exceptions.php"},{"name":"FacadeInterface.php","path":"VENDORPATH\\kint-php\\kint\\src\\FacadeInterface.php"},{"name":"Feature.php","path":"APPPATH\\Config\\Feature.php"},{"name":"Filters.php","path":"APPPATH\\Config\\Filters.php"},{"name":"FlatAuthorization.php","path":"VENDORPATH\\myth\\auth\\src\\Authorization\\FlatAuthorization.php"},{"name":"Functions.php","path":"VENDORPATH\\phpunit\\phpunit\\src\\Framework\\Assert\\Functions.php"},{"name":"GroupModel.php","path":"VENDORPATH\\myth\\auth\\src\\Authorization\\GroupModel.php"},{"name":"GroupModel.php","path":"VENDORPATH\\myth\\auth\\src\\Models\\GroupModel.php"},{"name":"InstalledVersions.php","path":"VENDORPATH\\composer\\InstalledVersions.php"},{"name":"Kint.php","path":"APPPATH\\Config\\Kint.php"},{"name":"Kint.php","path":"VENDORPATH\\kint-php\\kint\\src\\Kint.php"},{"name":"LocalAuthenticator.php","path":"VENDORPATH\\myth\\auth\\src\\Authentication\\LocalAuthenticator.php"},{"name":"LogLevel.php","path":"VENDORPATH\\psr\\log\\Psr\\Log\\LogLevel.php"},{"name":"Logger.php","path":"APPPATH\\Config\\Logger.php"},{"name":"LoggerAwareTrait.php","path":"VENDORPATH\\psr\\log\\Psr\\Log\\LoggerAwareTrait.php"},{"name":"LoggerInterface.php","path":"VENDORPATH\\psr\\log\\Psr\\Log\\LoggerInterface.php"},{"name":"LoginFilter.php","path":"VENDORPATH\\myth\\auth\\src\\Filters\\LoginFilter.php"},{"name":"LoginModel.php","path":"VENDORPATH\\myth\\auth\\src\\Models\\LoginModel.php"},{"name":"Modules.php","path":"APPPATH\\Config\\Modules.php"},{"name":"Paths.php","path":"APPPATH\\Config\\Paths.php"},{"name":"PermissionModel.php","path":"VENDORPATH\\myth\\auth\\src\\Authorization\\PermissionModel.php"},{"name":"PermissionModel.php","path":"VENDORPATH\\myth\\auth\\src\\Models\\PermissionModel.php"},{"name":"Registrar.php","path":"VENDORPATH\\myth\\auth\\src\\Config\\Registrar.php"},{"name":"RendererInterface.php","path":"VENDORPATH\\kint-php\\kint\\src\\Renderer\\RendererInterface.php"},{"name":"RichRenderer.php","path":"VENDORPATH\\kint-php\\kint\\src\\Renderer\\RichRenderer.php"},{"name":"Routes.php","path":"APPPATH\\Config\\Routes.php"},{"name":"Routes.php","path":"VENDORPATH\\myth\\auth\\src\\Config\\Routes.php"},{"name":"Security.php","path":"APPPATH\\Config\\Security.php"},{"name":"Services.php","path":"APPPATH\\Config\\Services.php"},{"name":"Services.php","path":"VENDORPATH\\myth\\auth\\src\\Config\\Services.php"},{"name":"Session.php","path":"APPPATH\\Config\\Session.php"},{"name":"TextRenderer.php","path":"VENDORPATH\\kint-php\\kint\\src\\Renderer\\TextRenderer.php"},{"name":"Toolbar.php","path":"APPPATH\\Config\\Toolbar.php"},{"name":"TransaksiModel.php","path":"APPPATH\\Models\\TransaksiModel.php"},{"name":"User.php","path":"VENDORPATH\\myth\\auth\\src\\Entities\\User.php"},{"name":"UserAgents.php","path":"APPPATH\\Config\\UserAgents.php"},{"name":"UserModel.php","path":"VENDORPATH\\myth\\auth\\src\\Models\\UserModel.php"},{"name":"Utils.php","path":"VENDORPATH\\kint-php\\kint\\src\\Utils.php"},{"name":"Validation.php","path":"APPPATH\\Config\\Validation.php"},{"name":"View.php","path":"APPPATH\\Config\\View.php"},{"name":"atas.php","path":"APPPATH\\Views\\atas.php"},{"name":"auth_helper.php","path":"VENDORPATH\\myth\\auth\\src\\Helpers\\auth_helper.php"},{"name":"autoload.php","path":"VENDORPATH\\autoload.php"},{"name":"autoload_real.php","path":"VENDORPATH\\composer\\autoload_real.php"},{"name":"autoload_static.php","path":"VENDORPATH\\composer\\autoload_static.php"},{"name":"bawah.php","path":"APPPATH\\Views\\bawah.php"},{"name":"bootstrap.php","path":"VENDORPATH\\symfony\\polyfill-ctype\\bootstrap.php"},{"name":"bootstrap.php","path":"VENDORPATH\\symfony\\polyfill-intl-grapheme\\bootstrap.php"},{"name":"bootstrap.php","path":"VENDORPATH\\symfony\\polyfill-intl-normalizer\\bootstrap.php"},{"name":"bootstrap.php","path":"VENDORPATH\\symfony\\polyfill-mbstring\\bootstrap.php"},{"name":"bootstrap.php","path":"VENDORPATH\\symfony\\polyfill-php80\\bootstrap.php"},{"name":"bootstrap.php","path":"VENDORPATH\\symfony\\polyfill-php81\\bootstrap.php"},{"name":"bootstrap80.php","path":"VENDORPATH\\symfony\\polyfill-ctype\\bootstrap80.php"},{"name":"bootstrap80.php","path":"VENDORPATH\\symfony\\polyfill-intl-normalizer\\bootstrap80.php"},{"name":"bootstrap80.php","path":"VENDORPATH\\symfony\\polyfill-mbstring\\bootstrap80.php"},{"name":"deep_copy.php","path":"VENDORPATH\\myclabs\\deep-copy\\src\\DeepCopy\\deep_copy.php"},{"name":"development.php","path":"APPPATH\\Config\\Boot\\development.php"},{"name":"edit_karyawan.php","path":"APPPATH\\Views\\edit_karyawan.php"},{"name":"footer.php","path":"APPPATH\\Views\\footer.php"},{"name":"function.php","path":"VENDORPATH\\symfony\\deprecation-contracts\\function.php"},{"name":"functions.php","path":"VENDORPATH\\symfony\\string\\Resources\\functions.php"},{"name":"index.php","path":"FCPATH\\index.php"},{"name":"init.php","path":"VENDORPATH\\kint-php\\kint\\init.php"},{"name":"init_helpers.php","path":"VENDORPATH\\kint-php\\kint\\init_helpers.php"},{"name":"installed.php","path":"VENDORPATH\\composer\\installed.php"},{"name":"linkatas.php","path":"APPPATH\\Views\\kumpulanlink\\linkatas.php"},{"name":"linkbawah.php","path":"APPPATH\\Views\\kumpulanscript\\linkbawah.php"},{"name":"navbar.php","path":"APPPATH\\Views\\navbar.php"},{"name":"platform_check.php","path":"VENDORPATH\\composer\\platform_check.php"},{"name":"sidebar.php","path":"APPPATH\\Views\\sidebar.php"}]},"badgeValue":196,"isEmpty":false,"hasTabContent":true,"hasLabel":false,"icon":"data:image\/png;base64,iVBORw0KGgoAAAANSUhEUgAAABgAAAAYCAYAAADgdz34AAAAAXNSR0IArs4c6QAAAARnQU1BAACxjwv8YQUAAAAJcEhZcwAADsMAAA7DAcdvqGQAAAGBSURBVEhL7ZQ9S8NQGIVTBQUncfMfCO4uLgoKbuKQOWg+OkXERRE1IAXrIHbVDrqIDuLiJgj+gro7S3dnpfq88b1FMTE3VZx64HBzzvvZWxKnj15QCcPwCD5HUfSWR+JtzgmtsUcQBEva5IIm9SwSu+95CAWbUuy67qBa32ByZEDpIaZYZSZMjjQuPcQUq8yEyYEb8FSerYeQVGbAFzJkX1PyQWLhgCz0BxTCekC1Wp0hsa6yokzhed4oje6Iz6rlJEkyIKfUEFtITVtQdAibn5rMyaYsMS+a5wTv8qeXMhcU16QZbKgl3hbs+L4\/pnpdc87MElZgq10p5DxGdq8I7xrvUWUKvG3NbSK7ubngYzdJwSsF7TiOh9VOgfcEz1UayNe3JUPM1RWC5GXYgTfc75B4NBmXJnAtTfpABX0iPvEd9ezALwkplCFXcr9styiNOKc1RRZpaPM9tcqBwlWzGY1qPL9wjqRBgF5BH6j8HWh2S7MHlX8PrmbK+k\/8PzjOOzx1D3i1pKTTAAAAAElFTkSuQmCC","hasTimelineData":false,"timelineData":[]},{"title":"Routes","titleSafe":"routes","titleDetails":"","display":{"matchedRoute":[{"directory":"","controller":"\\App\\Controllers\\DaftarKaryawanController","method":"edit_karyawan","paramCount":1,"truePCount":1,"params":[{"name":"$id_karyawan = ","value":"18"}]}],"routes":[{"method":"GET","route":"\/","handler":"\\App\\Controllers\\Home::dashboard"},{"method":"GET","route":"dashboard","handler":"\\App\\Controllers\\Home::dashboard"},{"method":"GET","route":"daftar_role","handler":"\\App\\Controllers\\DaftarRoleController::index"},{"method":"GET","route":"daftar_pengguna","handler":"\\App\\Controllers\\DaftarPenggunaController::index"},{"method":"GET","route":"daftar_sertifikat","handler":"\\App\\Controllers\\DaftarSertifikatController::index"},{"method":"GET","route":"daftar_karyawan","handler":"\\App\\Controllers\\DaftarKaryawanController::index"},{"method":"GET","route":"daftar_jabatan","handler":"\\App\\Controllers\\DaftarJabatanController::index"},{"method":"GET","route":"daftar_divisi","handler":"\\App\\Controllers\\DaftarDivisiController::index"},{"method":"GET","route":"karyawan","handler":"\\App\\Controllers\\DaftarKaryawanController::index_karyawan"},{"method":"GET","route":"tambah_role","handler":"\\App\\Controllers\\DaftarRoleController::tambah_role"},{"method":"GET","route":"tambah_pengguna","handler":"\\App\\Controllers\\DaftarPenggunaController::tambah_pengguna"},{"method":"GET","route":"tambah_sertifikat","handler":"\\App\\Controllers\\DaftarSertifikatController::tambah_sertifikat"},{"method":"GET","route":"tambah_karyawan","handler":"\\App\\Controllers\\DaftarKaryawanController::tambah_karyawan"},{"method":"GET","route":"tambah_jabatan","handler":"\\App\\Controllers\\DaftarJabatanController::tambah_jabatan"},{"method":"GET","route":"tambah_divisi","handler":"\\App\\Controllers\\DaftarDivisiController::tambah_divisi"},{"method":"GET","route":"edit_role\/([0-9]+)","handler":"\\App\\Controllers\\DaftarRoleController::edit_role\/$1"},{"method":"GET","route":"edit_pengguna\/([0-9]+)","handler":"\\App\\Controllers\\DaftarPenggunaController::edit_pengguna\/$1"},{"method":"GET","route":"edit_sertifikat\/([0-9]+)","handler":"\\App\\Controllers\\DaftarSertifikatController::edit_sertifikat\/$1"},{"method":"GET","route":"edit_karyawan\/([0-9]+)","handler":"\\App\\Controllers\\DaftarKaryawanController::edit_karyawan\/$1"},{"method":"GET","route":"edit_jabatan\/([0-9]+)","handler":"\\App\\Controllers\\DaftarJabatanController::edit_jabatan\/$1"},{"method":"GET","route":"edit_divisi\/([0-9]+)","handler":"\\App\\Controllers\\DaftarDivisiController::edit_divisi\/$1"},{"method":"GET","route":"edit_karyawandisable\/([0-9]+)","handler":"\\App\\Controllers\\DaftarKaryawanController::edit_karyawandisable\/$1"},{"method":"GET","route":"delete_role\/([0-9]+)","handler":"\\App\\Controllers\\DaftarRoleController::delete_role\/$1"},{"method":"GET","route":"delete_pengguna\/([0-9]+)","handler":"\\App\\Controllers\\DaftarPenggunaController::delete_pengguna\/$1"},{"method":"GET","route":"delete_sertifikat\/([0-9]+)","handler":"\\App\\Controllers\\DaftarSertifikatController::delete_sertifikat\/$1"},{"method":"GET","route":"delete_sertifikatkaryawan\/([0-9]+)","handler":"\\App\\Controllers\\TransaksiController::delete_sertifikatkaryawan\/$1"},{"method":"GET","route":"delete_karyawan\/([0-9]+)","handler":"\\App\\Controllers\\DaftarKaryawanController::delete_karyawan\/$1"},{"method":"GET","route":"delete_jabatan\/([0-9]+)","handler":"\\App\\Controllers\\DaftarJabatanController::delete_jabatan\/$1"},{"method":"GET","route":"delete_divisi\/([0-9]+)","handler":"\\App\\Controllers\\DaftarDivisiController::delete_divisi\/$1"},{"method":"GET","route":"lihat_karyawan\/([0-9]+)","handler":"\\App\\Controllers\\DaftarKaryawanController::lihat_karyawan\/$1"},{"method":"GET","route":"login","handler":"\\Myth\\Auth\\Controllers\\AuthController::login"},{"method":"GET","route":"logout","handler":"\\Myth\\Auth\\Controllers\\AuthController::logout"},{"method":"GET","route":"register","handler":"\\Myth\\Auth\\Controllers\\AuthController::register"},{"method":"GET","route":"activate-account","handler":"\\Myth\\Auth\\Controllers\\AuthController::activateAccount"},{"method":"GET","route":"resend-activate-account","handler":"\\Myth\\Auth\\Controllers\\AuthController::resendActivateAccount"},{"method":"GET","route":"forgot","handler":"\\Myth\\Auth\\Controllers\\AuthController::forgotPassword"},{"method":"GET","route":"reset-password","handler":"\\Myth\\Auth\\Controllers\\AuthController::resetPassword"},{"method":"POST","route":"dashboard","handler":"\\App\\Controllers\\Home::dashboard"},{"method":"POST","route":"simpan_role","handler":"\\App\\Controllers\\DaftarRoleController::simpan_role"},{"method":"POST","route":"simpan_pengguna","handler":"\\App\\Controllers\\DaftarPenggunaController::simpan_pengguna"},{"method":"POST","route":"simpan_sertifikat","handler":"\\App\\Controllers\\DaftarSertifikatController::simpan_sertifikat"},{"method":"POST","route":"simpan_karyawan","handler":"\\App\\Controllers\\DaftarKaryawanController::simpan_karyawan"},{"method":"POST","route":"simpan_jabatan","handler":"\\App\\Controllers\\DaftarJabatanController::simpan_jabatan"},{"method":"POST","route":"simpan_divisi","handler":"\\App\\Controllers\\DaftarDivisiController::simpan_divisi"},{"method":"POST","route":"simpan_sertifikatkaryawan","handler":"\\App\\Controllers\\TransaksiController::simpan_sertifikatkaryawan"},{"method":"POST","route":"login","handler":"\\Myth\\Auth\\Controllers\\AuthController::attemptLogin"},{"method":"POST","route":"register","handler":"\\Myth\\Auth\\Controllers\\AuthController::attemptRegister"},{"method":"POST","route":"forgot","handler":"\\Myth\\Auth\\Controllers\\AuthController::attemptForgot"},{"method":"POST","route":"reset-password","handler":"\\Myth\\Auth\\Controllers\\AuthController::attemptReset"},{"method":"PUT","route":"update_role\/([0-9]+)","handler":"\\App\\Controllers\\DaftarRoleController::update_role\/$1"},{"method":"PUT","route":"update_pengguna\/([0-9]+)","handler":"\\App\\Controllers\\DaftarPenggunaController::update_pengguna\/$1"},{"method":"PUT","route":"update_sertifikat\/([0-9]+)","handler":"\\App\\Controllers\\DaftarSertifikatController::update_sertifikat\/$1"},{"method":"PUT","route":"update_karyawan\/([0-9]+)","handler":"\\App\\Controllers\\DaftarKaryawanController::update_karyawan\/$1"},{"method":"PUT","route":"update_jabatan\/([0-9]+)","handler":"\\App\\Controllers\\DaftarJabatanController::update_jabatan\/$1"},{"method":"PUT","route":"update_divisi\/([0-9]+)","handler":"\\App\\Controllers\\DaftarDivisiController::update_divisi\/$1"}]},"badgeValue":37,"isEmpty":false,"hasTabContent":true,"hasLabel":false,"icon":"data:image\/png;base64,iVBORw0KGgoAAAANSUhEUgAAABgAAAAYCAYAAADgdz34AAAAAXNSR0IArs4c6QAAAARnQU1BAACxjwv8YQUAAAAJcEhZcwAADsMAAA7DAcdvqGQAAAFDSURBVEhL7ZRNSsNQFIUjVXSiOFEcuQIHDpzpxC0IGYeE\/BEInbWlCHEDLsSiuANdhKDjgm6ggtSJ+l25ldrmmTwIgtgDh\/t37r1J+16cX0dRFMtpmu5pWAkrvYjjOB7AETzStBFW+inxu3KUJMmhludQpoflS1zXban4LYqiO224h6VLTHr8Z+z8EpIHFF9gG78nDVmW7UgTHKjsCyY98QP+pcq+g8Ku2s8G8X3f3\/I8b038WZTp+bO38zxfFd+I6YY6sNUvFlSDk9CRhiAI1jX1I9Cfw7GG1UB8LAuwbU0ZwQnbRDeEN5qqBxZMLtE1ti9LtbREnMIuOXnyIf5rGIb7Wq8HmlZgwYBH7ORTcKH5E4mpjeGt9fBZcHE2GCQ3Vt7oTNPNg+FXLHnSsHkw\/FR+Gg2bB8Ptzrst\/v6C\/wrH+QB+duli6MYJdQAAAABJRU5ErkJggg==","hasTimelineData":false,"timelineData":[]},{"title":"Events","titleSafe":"events","titleDetails":"","display":{"events":{"pre_system":{"event":"pre_system","duration":"9.08","count":1},"dbquery":{"event":"dbquery","duration":"0.37","count":9}}},"badgeValue":10,"isEmpty":false,"hasTabContent":true,"hasLabel":false,"icon":"data:image\/png;base64,iVBORw0KGgoAAAANSUhEUgAAABgAAAAYCAYAAADgdz34AAAAAXNSR0IArs4c6QAAAARnQU1BAACxjwv8YQUAAAAJcEhZcwAADsMAAA7DAcdvqGQAAAEASURBVEhL7ZXNDcIwDIVTsRBH1uDQDdquUA6IM1xgCA6MwJUN2hk6AQzAz0vl0ETUxC5VT3zSU5w81\/mRMGZysixbFEVR0jSKNt8geQU9aRpFmp\/keX6AbjZ5oB74vsaN5lSzA4tLSjpBFxsjeSuRy4d2mDdQTWU7YLbXTNN05mKyovj5KL6B7q3hoy3KwdZxBlT+Ipz+jPHrBqOIynZgcZonoukb\/0ckiTHqNvDXtXEAaygRbaB9FvUTjRUHsIYS0QaSp+Dw6wT4hiTmYHOcYZsdLQ2CbXa4ftuuYR4x9vYZgdb4vsFYUdmABMYeukK9\/SUme3KMFQ77+Yfzh8eYF8+orDuDWU5LAAAAAElFTkSuQmCC","hasTimelineData":true,"timelineData":[{"name":"Event: pre_system","component":"Events","start":1694927052.285378,"duration":0.009076118469238281},{"name":"Event: dbquery","component":"Events","start":1694927052.450908,"duration":7.510185241699219e-5},{"name":"Event: dbquery","component":"Events","start":1694927052.463,"duration":4.1961669921875e-5},{"name":"Event: dbquery","component":"Events","start":1694927052.464915,"duration":3.0040740966796875e-5},{"name":"Event: dbquery","component":"Events","start":1694927052.465517,"duration":2.8848648071289062e-5},{"name":"Event: dbquery","component":"Events","start":1694927052.465861,"duration":2.6941299438476562e-5},{"name":"Event: dbquery","component":"Events","start":1694927052.466201,"duration":2.6941299438476562e-5},{"name":"Event: dbquery","component":"Events","start":1694927052.468976,"duration":4.601478576660156e-5},{"name":"Event: dbquery","component":"Events","start":1694927052.471768,"duration":4.410743713378906e-5},{"name":"Event: dbquery","component":"Events","start":1694927052.473652,"duration":5.221366882324219e-5}]}],"vars":{"varData":{"View Data":{"transaksi":"<div class=\"kint-rich\"><dl><dt class=\"kint-parent\"><span class=\"kint-popup-trigger\" title=\"Open in new window\">&boxbox;<\/span><span class=\"kint-search-trigger\" title=\"Show search box\">&telrec;<\/span><input type=\"text\" class=\"kint-search\" value=\"\"><nav><\/nav><dfn>$value<\/dfn> <var>array<\/var> (1)<\/dt><dd><dl><dt class=\"kint-parent\"><span class=\"kint-access-path-trigger\" title=\"Show access path\">&rlarr;<\/span><span class=\"kint-popup-trigger\" title=\"Open in new window\">&boxbox;<\/span><nav><\/nav><dfn>0<\/dfn> =&gt; <var>array<\/var> (7)<div class=\"access-path\">$value[0]<\/div><\/dt><dd><dl><dt><span class=\"kint-access-path-trigger\" title=\"Show access path\">&rlarr;<\/span><dfn>id_sertifikat<\/dfn> =&gt; <var>string<\/var> (1) \"5\"<div class=\"access-path\">$value[0]['id_sertifikat']<\/div><\/dt><\/dl><dl><dt><span class=\"kint-access-path-trigger\" title=\"Show access path\">&rlarr;<\/span><dfn>kode_sertifikat<\/dfn> =&gt; <var>string<\/var> (6) \"123452\"<div class=\"access-path\">$value[0]['kode_sertifikat']<\/div><\/dt><\/dl><dl><dt><span class=\"kint-access-path-trigger\" title=\"Show access path\">&rlarr;<\/span><dfn>nama_sertifikat<\/dfn> =&gt; <var>string<\/var> (6) \"TEST 2\"<div class=\"access-path\">$value[0]['nama_sertifikat']<\/div><\/dt><\/dl><dl><dt><span class=\"kint-access-path-trigger\" title=\"Show access path\">&rlarr;<\/span><dfn>id_transaksi<\/dfn> =&gt; <var>string<\/var> (2) \"15\"<div class=\"access-path\">$value[0]['id_transaksi']<\/div><\/dt><\/dl><dl><dt><span class=\"kint-access-path-trigger\" title=\"Show access path\">&rlarr;<\/span><dfn>id_karyawan<\/dfn> =&gt; <var>string<\/var> (2) \"18\"<div class=\"access-path\">$value[0]['id_karyawan']<\/div><\/dt><\/dl><dl><dt><span class=\"kint-access-path-trigger\" title=\"Show access path\">&rlarr;<\/span><dfn>tanggal_ambil<\/dfn> =&gt; <var>string<\/var> (10) \"2023-09-01\"<div class=\"access-path\">$value[0]['tanggal_ambil']<\/div><\/dt><\/dl><dl><dt><span class=\"kint-access-path-trigger\" title=\"Show access path\">&rlarr;<\/span><dfn>tanggal_ekspire<\/dfn> =&gt; <var>string<\/var> (10) \"2023-09-30\"<div class=\"access-path\">$value[0]['tanggal_ekspire']<\/div><\/dt><\/dl><\/dd><\/dl><\/dd><\/dl><\/div>","sertifikat":"<div class=\"kint-rich\"><dl><dt class=\"kint-parent\"><span class=\"kint-popup-trigger\" title=\"Open in new window\">&boxbox;<\/span><span class=\"kint-search-trigger\" title=\"Show search box\">&telrec;<\/span><input type=\"text\" class=\"kint-search\" value=\"\"><nav><\/nav><dfn>$value<\/dfn> <var>array<\/var> (4)<\/dt><dd><ul class=\"kint-tabs\"><li class=\"kint-active-tab\">Table (4)<\/li><li>Contents (4)<\/li><\/ul><ul class=\"kint-tab-contents\"><li class=\"kint-show\"><pre><table><thead><tr><th><\/th><th>id_sertifikat<\/th><th>kode_sertifikat<\/th><th>nama_sertifikat<\/th><\/tr><\/thead><tbody><tr><th>0<\/th><td title=\"string (1)\">1<\/td><td title=\"string (5)\">16949<\/td><td title=\"string (16)\">SERTIFIKASI IATF<\/td><\/tr><tr><th>1<\/th><td title=\"string (1)\">3<\/td><td title=\"string (5)\">14001<\/td><td title=\"string (15)\">SERTIFIKASI ISO<\/td><\/tr><tr><th>2<\/th><td title=\"string (1)\">4<\/td><td title=\"string (4)\">0098<\/td><td title=\"string (15)\">SERTIFIKASI SNI<\/td><\/tr><tr><th>3<\/th><td title=\"string (1)\">5<\/td><td title=\"string (6)\">123452<\/td><td title=\"string (6)\">TEST 2<\/td><\/tr><\/tbody><\/table><\/pre><\/li><li><dl><dt class=\"kint-parent\"><span class=\"kint-access-path-trigger\" title=\"Show access path\">&rlarr;<\/span><span class=\"kint-popup-trigger\" title=\"Open in new window\">&boxbox;<\/span><nav><\/nav><dfn>0<\/dfn> =&gt; <var>array<\/var> (3)<div class=\"access-path\">$value[0]<\/div><\/dt><dd><dl><dt><span class=\"kint-access-path-trigger\" title=\"Show access path\">&rlarr;<\/span><dfn>id_sertifikat<\/dfn> =&gt; <var>string<\/var> (1) \"1\"<div class=\"access-path\">$value[0]['id_sertifikat']<\/div><\/dt><\/dl><dl><dt><span class=\"kint-access-path-trigger\" title=\"Show access path\">&rlarr;<\/span><dfn>kode_sertifikat<\/dfn> =&gt; <var>string<\/var> (5) \"16949\"<div class=\"access-path\">$value[0]['kode_sertifikat']<\/div><\/dt><\/dl><dl><dt><span class=\"kint-access-path-trigger\" title=\"Show access path\">&rlarr;<\/span><dfn>nama_sertifikat<\/dfn> =&gt; <var>string<\/var> (16) \"SERTIFIKASI IATF\"<div class=\"access-path\">$value[0]['nama_sertifikat']<\/div><\/dt><\/dl><\/dd><\/dl><dl><dt class=\"kint-parent\"><span class=\"kint-access-path-trigger\" title=\"Show access path\">&rlarr;<\/span><span class=\"kint-popup-trigger\" title=\"Open in new window\">&boxbox;<\/span><nav><\/nav><dfn>1<\/dfn> =&gt; <var>array<\/var> (3)<div class=\"access-path\">$value[1]<\/div><\/dt><dd><dl><dt><span class=\"kint-access-path-trigger\" title=\"Show access path\">&rlarr;<\/span><dfn>id_sertifikat<\/dfn> =&gt; <var>string<\/var> (1) \"3\"<div class=\"access-path\">$value[1]['id_sertifikat']<\/div><\/dt><\/dl><dl><dt><span class=\"kint-access-path-trigger\" title=\"Show access path\">&rlarr;<\/span><dfn>kode_sertifikat<\/dfn> =&gt; <var>string<\/var> (5) \"14001\"<div class=\"access-path\">$value[1]['kode_sertifikat']<\/div><\/dt><\/dl><dl><dt><span class=\"kint-access-path-trigger\" title=\"Show access path\">&rlarr;<\/span><dfn>nama_sertifikat<\/dfn> =&gt; <var>string<\/var> (15) \"SERTIFIKASI ISO\"<div class=\"access-path\">$value[1]['nama_sertifikat']<\/div><\/dt><\/dl><\/dd><\/dl><dl><dt class=\"kint-parent\"><span class=\"kint-access-path-trigger\" title=\"Show access path\">&rlarr;<\/span><span class=\"kint-popup-trigger\" title=\"Open in new window\">&boxbox;<\/span><nav><\/nav><dfn>2<\/dfn> =&gt; <var>array<\/var> (3)<div class=\"access-path\">$value[2]<\/div><\/dt><dd><dl><dt><span class=\"kint-access-path-trigger\" title=\"Show access path\">&rlarr;<\/span><dfn>id_sertifikat<\/dfn> =&gt; <var>string<\/var> (1) \"4\"<div class=\"access-path\">$value[2]['id_sertifikat']<\/div><\/dt><\/dl><dl><dt><span class=\"kint-access-path-trigger\" title=\"Show access path\">&rlarr;<\/span><dfn>kode_sertifikat<\/dfn> =&gt; <var>string<\/var> (4) \"0098\"<div class=\"access-path\">$value[2]['kode_sertifikat']<\/div><\/dt><\/dl><dl><dt><span class=\"kint-access-path-trigger\" title=\"Show access path\">&rlarr;<\/span><dfn>nama_sertifikat<\/dfn> =&gt; <var>string<\/var> (15) \"SERTIFIKASI SNI\"<div class=\"access-path\">$value[2]['nama_sertifikat']<\/div><\/dt><\/dl><\/dd><\/dl><dl><dt class=\"kint-parent\"><span class=\"kint-access-path-trigger\" title=\"Show access path\">&rlarr;<\/span><span class=\"kint-popup-trigger\" title=\"Open in new window\">&boxbox;<\/span><nav><\/nav><dfn>3<\/dfn> =&gt; <var>array<\/var> (3)<div class=\"access-path\">$value[3]<\/div><\/dt><dd><dl><dt><span class=\"kint-access-path-trigger\" title=\"Show access path\">&rlarr;<\/span><dfn>id_sertifikat<\/dfn> =&gt; <var>string<\/var> (1) \"5\"<div class=\"access-path\">$value[3]['id_sertifikat']<\/div><\/dt><\/dl><dl><dt><span class=\"kint-access-path-trigger\" title=\"Show access path\">&rlarr;<\/span><dfn>kode_sertifikat<\/dfn> =&gt; <var>string<\/var> (6) \"123452\"<div class=\"access-path\">$value[3]['kode_sertifikat']<\/div><\/dt><\/dl><dl><dt><span class=\"kint-access-path-trigger\" title=\"Show access path\">&rlarr;<\/span><dfn>nama_sertifikat<\/dfn> =&gt; <var>string<\/var> (6) \"TEST 2\"<div class=\"access-path\">$value[3]['nama_sertifikat']<\/div><\/dt><\/dl><\/dd><\/dl><\/li><\/ul><\/dd><\/dl><\/div>","jenissertifikat":"<div class=\"kint-rich\"><dl><dt class=\"kint-parent\"><span class=\"kint-popup-trigger\" title=\"Open in new window\">&boxbox;<\/span><span class=\"kint-search-trigger\" title=\"Show search box\">&telrec;<\/span><input type=\"text\" class=\"kint-search\" value=\"\"><nav><\/nav><dfn>$value<\/dfn> <var>array<\/var> (4)<\/dt><dd><ul class=\"kint-tabs\"><li class=\"kint-active-tab\">Table (4)<\/li><li>Contents (4)<\/li><\/ul><ul class=\"kint-tab-contents\"><li class=\"kint-show\"><pre><table><thead><tr><th><\/th><th>id_sertifikat<\/th><th>kode_sertifikat<\/th><th>nama_sertifikat<\/th><\/tr><\/thead><tbody><tr><th>0<\/th><td title=\"string (1)\">1<\/td><td title=\"string (5)\">16949<\/td><td title=\"string (16)\">SERTIFIKASI IATF<\/td><\/tr><tr><th>1<\/th><td title=\"string (1)\">3<\/td><td title=\"string (5)\">14001<\/td><td title=\"string (15)\">SERTIFIKASI ISO<\/td><\/tr><tr><th>2<\/th><td title=\"string (1)\">4<\/td><td title=\"string (4)\">0098<\/td><td title=\"string (15)\">SERTIFIKASI SNI<\/td><\/tr><tr><th>3<\/th><td title=\"string (1)\">5<\/td><td title=\"string (6)\">123452<\/td><td title=\"string (6)\">TEST 2<\/td><\/tr><\/tbody><\/table><\/pre><\/li><li><dl><dt class=\"kint-parent\"><span class=\"kint-access-path-trigger\" title=\"Show access path\">&rlarr;<\/span><span class=\"kint-popup-trigger\" title=\"Open in new window\">&boxbox;<\/span><nav><\/nav><dfn>0<\/dfn> =&gt; <var>array<\/var> (3)<div class=\"access-path\">$value[0]<\/div><\/dt><dd><dl><dt><span class=\"kint-access-path-trigger\" title=\"Show access path\">&rlarr;<\/span><dfn>id_sertifikat<\/dfn> =&gt; <var>string<\/var> (1) \"1\"<div class=\"access-path\">$value[0]['id_sertifikat']<\/div><\/dt><\/dl><dl><dt><span class=\"kint-access-path-trigger\" title=\"Show access path\">&rlarr;<\/span><dfn>kode_sertifikat<\/dfn> =&gt; <var>string<\/var> (5) \"16949\"<div class=\"access-path\">$value[0]['kode_sertifikat']<\/div><\/dt><\/dl><dl><dt><span class=\"kint-access-path-trigger\" title=\"Show access path\">&rlarr;<\/span><dfn>nama_sertifikat<\/dfn> =&gt; <var>string<\/var> (16) \"SERTIFIKASI IATF\"<div class=\"access-path\">$value[0]['nama_sertifikat']<\/div><\/dt><\/dl><\/dd><\/dl><dl><dt class=\"kint-parent\"><span class=\"kint-access-path-trigger\" title=\"Show access path\">&rlarr;<\/span><span class=\"kint-popup-trigger\" title=\"Open in new window\">&boxbox;<\/span><nav><\/nav><dfn>1<\/dfn> =&gt; <var>array<\/var> (3)<div class=\"access-path\">$value[1]<\/div><\/dt><dd><dl><dt><span class=\"kint-access-path-trigger\" title=\"Show access path\">&rlarr;<\/span><dfn>id_sertifikat<\/dfn> =&gt; <var>string<\/var> (1) \"3\"<div class=\"access-path\">$value[1]['id_sertifikat']<\/div><\/dt><\/dl><dl><dt><span class=\"kint-access-path-trigger\" title=\"Show access path\">&rlarr;<\/span><dfn>kode_sertifikat<\/dfn> =&gt; <var>string<\/var> (5) \"14001\"<div class=\"access-path\">$value[1]['kode_sertifikat']<\/div><\/dt><\/dl><dl><dt><span class=\"kint-access-path-trigger\" title=\"Show access path\">&rlarr;<\/span><dfn>nama_sertifikat<\/dfn> =&gt; <var>string<\/var> (15) \"SERTIFIKASI ISO\"<div class=\"access-path\">$value[1]['nama_sertifikat']<\/div><\/dt><\/dl><\/dd><\/dl><dl><dt class=\"kint-parent\"><span class=\"kint-access-path-trigger\" title=\"Show access path\">&rlarr;<\/span><span class=\"kint-popup-trigger\" title=\"Open in new window\">&boxbox;<\/span><nav><\/nav><dfn>2<\/dfn> =&gt; <var>array<\/var> (3)<div class=\"access-path\">$value[2]<\/div><\/dt><dd><dl><dt><span class=\"kint-access-path-trigger\" title=\"Show access path\">&rlarr;<\/span><dfn>id_sertifikat<\/dfn> =&gt; <var>string<\/var> (1) \"4\"<div class=\"access-path\">$value[2]['id_sertifikat']<\/div><\/dt><\/dl><dl><dt><span class=\"kint-access-path-trigger\" title=\"Show access path\">&rlarr;<\/span><dfn>kode_sertifikat<\/dfn> =&gt; <var>string<\/var> (4) \"0098\"<div class=\"access-path\">$value[2]['kode_sertifikat']<\/div><\/dt><\/dl><dl><dt><span class=\"kint-access-path-trigger\" title=\"Show access path\">&rlarr;<\/span><dfn>nama_sertifikat<\/dfn> =&gt; <var>string<\/var> (15) \"SERTIFIKASI SNI\"<div class=\"access-path\">$value[2]['nama_sertifikat']<\/div><\/dt><\/dl><\/dd><\/dl><dl><dt class=\"kint-parent\"><span class=\"kint-access-path-trigger\" title=\"Show access path\">&rlarr;<\/span><span class=\"kint-popup-trigger\" title=\"Open in new window\">&boxbox;<\/span><nav><\/nav><dfn>3<\/dfn> =&gt; <var>array<\/var> (3)<div class=\"access-path\">$value[3]<\/div><\/dt><dd><dl><dt><span class=\"kint-access-path-trigger\" title=\"Show access path\">&rlarr;<\/span><dfn>id_sertifikat<\/dfn> =&gt; <var>string<\/var> (1) \"5\"<div class=\"access-path\">$value[3]['id_sertifikat']<\/div><\/dt><\/dl><dl><dt><span class=\"kint-access-path-trigger\" title=\"Show access path\">&rlarr;<\/span><dfn>kode_sertifikat<\/dfn> =&gt; <var>string<\/var> (6) \"123452\"<div class=\"access-path\">$value[3]['kode_sertifikat']<\/div><\/dt><\/dl><dl><dt><span class=\"kint-access-path-trigger\" title=\"Show access path\">&rlarr;<\/span><dfn>nama_sertifikat<\/dfn> =&gt; <var>string<\/var> (6) \"TEST 2\"<div class=\"access-path\">$value[3]['nama_sertifikat']<\/div><\/dt><\/dl><\/dd><\/dl><\/li><\/ul><\/dd><\/dl><\/div>","karyawan":"<div class=\"kint-rich\"><dl><dt class=\"kint-parent\"><span class=\"kint-popup-trigger\" title=\"Open in new window\">&boxbox;<\/span><span class=\"kint-search-trigger\" title=\"Show search box\">&telrec;<\/span><input type=\"text\" class=\"kint-search\" value=\"\"><nav><\/nav><dfn>$value<\/dfn> <var>array<\/var> (8)<\/dt><dd><dl><dt><span class=\"kint-access-path-trigger\" title=\"Show access path\">&rlarr;<\/span><dfn>id_karyawan<\/dfn> =&gt; <var>string<\/var> (2) \"18\"<div class=\"access-path\">$value['id_karyawan']<\/div><\/dt><\/dl><dl><dt><span class=\"kint-access-path-trigger\" title=\"Show access path\">&rlarr;<\/span><dfn>nama_karyawan<\/dfn> =&gt; <var>string<\/var> (12) \"YULPIKA SARI\"<div class=\"access-path\">$value['nama_karyawan']<\/div><\/dt><\/dl><dl><dt><span class=\"kint-access-path-trigger\" title=\"Show access path\">&rlarr;<\/span><dfn>alamat<\/dfn> =&gt; <var>string<\/var> (6) \"PADANG\"<div class=\"access-path\">$value['alamat']<\/div><\/dt><\/dl><dl><dt class=\"kint-parent\"><span class=\"kint-access-path-trigger\" title=\"Show access path\">&rlarr;<\/span><span class=\"kint-popup-trigger\" title=\"Open in new window\">&boxbox;<\/span><nav><\/nav><dfn>qr_code<\/dfn> =&gt; <var>string<\/var> (21662) \"data:image\/png;base64,iVBORw0KGgoAAAANSUhEUgAAAUAAAAFZCAIAAABmK2GuAAAACXBIWX...<div class=\"access-path\">$value['qr_code']<\/div><\/dt><dd><pre>data:image\/png;base64,iVBORw0KGgoAAAANSUhEUgAAAUAAAAFZCAIAAABmK2GuAAAACXBIWXMAAA7EAAAOxAGVKw4bAAAgAElEQVR4nO2dd3wdxdX3z9ymq16tYrlbcm9yx9imGTDE1BCHh0BCCBDSeAIhCUlIPoQQkvAmPHlSyBNwgIcAT0IIoWOIqQbjgnvvsiwXSVax1aV777x\/7O7Mmdm91xa2dTXmfD\/EudqdnZ1yfuec2d27l3HOgSAIM\/EluwEEQXxySMAEYTAkYIIwGBIwQRgMCZggDIYETBAGQwImCIMhAROEwZCACcJgSMAEYTAkYIIwGBIwQRgMCZggDIYETBAGE+hRacbYaWpHsjh936ZMPFZ981ucJ9PmvnmsifTINigCE4TBkIAJwmBIwARhMCRggjAYEjBBGAwJmCAMhgRMEAZDAiYIgyEBE4TB9OxJrMSY+HTR6as5WaNxMv09mTb3zeelznibpAhMEAZDAiYIgyEBE4TBkIAJwmBIwARhMCRggjAYEjBBGAwJmCAMhgRMEAZzKp\/ESszpexbHxPdamfgWqDPv7VMm2qQGRWCCMBgSMEEYDAmYIAyGBEwQBkMCJgiDIQEThMGQgAnCYEjABGEwJGCCMJjeexLLRE7fb+r1zbdPJev5sL755iojoAhMEAZDAiYIgyEBE4TBkIAJwmBIwARhMCRggjAYEjBBGAwJmCAMhgRMEAZDT2L1RZL1u4en7\/mwxPTN33k0AorABGEwJGCCMBgSMEEYDAmYIAyGBEwQBkMCJgiDIQEThMGQgAnCYEjABGEwvfck1pn3PE3ffEfUybTq9L0Tq2\/Oft9sVY+gCEwQBkMCJgiDIQEThMGQgAnCYEjABGEwJGCCMBgSMEEYDAmYIAyGBEwQBnMqn8Q6mWeP+ian7+mi0\/dUU7J+YbBvcub1SIMiMEEYDAmYIAyGBEwQBkMCJgiDIQEThMGQgAnCYEjABGEwJGCCMBgSMEEYDDsDXgt0+jh9T2L1zTdI9c1WEQmgCEwQBkMCJgiDIQEThMGQgAnCYEjABGEwJGCCMBgSMEEYDAmYIAyGBEwQBtOzJ7FO3xuGTHxX0+l7MilZv2yYLJJlVydDH3lqjSIwQRgMCZggDIYETBAGQwImCIMhAROEwZCACcJgSMAEYTAkYIIwGBIwQRjMqXwS69P2jqjEmPgbgn3zNxNPhjP+vBSBCcJgSMAEYTAkYIIwGBIwQRgMCZggDIYETBAGQwImCIMhAROEwZCACcJgAqewrr751MvJcOY9W9Y3n\/FKTLLeEGbEc4cUgQnCYEjABGEwJGCCMBgSMEEYDAmYIAyGBEwQBkMCJgiDIQEThMGQgAnCYHr2JNaZ9xuCidvcN3uULEz83cOT4WT622tKoQhMEAZDAiYIgyEBE4TBkIAJwmBO5dcJT4RjzZ27Kuvd2\/uVjLNW\/dbqngMw518AWLPxYII6tWOtwwWJjy0oGQfOsfgo7U9Qd7nPAqjBXC3JvXYlblViRJt71DZr44mMhrvv7ASOPX30KxkH8acDUIPdH3q5zaPL+6WGg715xp79MsNx6jqBbzmuWL3\/lrv\/BYwB5\/a\/AMCYFKumRRAbOVj1iwYz5wAuPjt\/2nU6qhF7xUlxVbjZHBdGrXG3h6HC+E\/tFO6jZBeY\/Q9uBm6z9Vn2TG2tdnZwNQAPqNJH1bWA6zPuvtYjzoEBcHVA8HiKORXgBitdc+Yd1AkVW3AvFF\/InS3M21oAPLbrg49P55oFwCXVKVC6A7gvPgbP\/c91ZUPzXa3ROYXfB+7tCGz3WwwEnngLz64xZwc2I7nXXQmWENrLVD1r1sZdUgf8J2qf0khuN08\/FgcDbIVYCdzZibpvNUmaqRw25bN1Ciw83basfR66BHC5GL0U6j4eTJlLxJkyzS\/j0RDbOZddZi7PwZzmuafD3VMQQ625Ii7HR+u66JHSeJcZJLY0XAmzW8v1QewNen8NjHRrIYaScwBuz5z1GeJYLYg9zsxhudr\/j8xFiQzIJjyMGLln2RIRK9yNcVohK5FW5pT0ShyETWM3gdsPqp1Zf2LXI\/ui1qA1AJyBxXiGSrsnrkCktIR55ReoVZ4za02T8KGyy1wtpo6SPdfxHZm+WHE+K7kJk62yP6OqPIdX2ph2Lq6PD3M5ml6n9wWM5Cpk4E7k7DnWHK0FjoFq4OJY21gqKITqJoIiHgddCVoZvEv0wu13NWErrocj40BGjBFmhx0QoKpkSRzWvArI9gh\/hFroYXZOSdEUGTPjh2v3eRUnBU5IdBdm0mHp6wjZBLukSElkeSYlhL2t1gzx2S6A+q67YGQJePbliV3pjGW9PUl6Ty2nUsA8IU4pNQkBQBmmFo6UuCaPcie3VgFRm2dirKkXVy7ds5YOuGrgKE1IcFVF8xHCKLGD0DICbHw4zMr\/8GAwVzvVfE+LhFo33b3D\/3LXvKh9U3xWPMONG+FdvoDjjNcZXrlfnVZrC07s7Q1ooLTEW9QpSrp7DU4AUOzQ6a8+UNr4KB5hytQp7ATwHrRPRJIiMI4wWqaHk2HlOGfRaK9tHBXpw6ENPbqiI4OPk9GBart4HSvyKFGDOJyLBEE07AQMWh0ApyrUAGkWccCq0EOosGnQbU5bR8jexWmk9GJ46YtOpLVTyS9AphiyYeJaFNNl4xYzcw7BlYsOKif1spO42Sy+qge2j8BCVXaqXVMcq3r5U\/M+ySB594Hdds8cjeF0CPtIaT3MY\/IAGZ8tMFfGyEBxmdyjDtE+3b9KG9ZOqq6W8RarHk0GODTJoIIU4s6TpXPhUj+2JtX2y447Jo4js95F7DhQDiJcpMwdRN4hDnTFc9lqZ6PbG+qx1\/6EalO9uYcwtPlF7gniTI3M5FE0xt5E5nTOSeXZmToIYhfqJo\/vuE8\/vX8V2kHLduyN4K0nT8\/qMbsMmOrdT9AzciQMqSqhYjzBTnncBk8HLH2NKgZcXngJ5dII3qeNidAGoBq0XMBSOx4Epx5NM9IXiDMgHyeaIXWomanqH5U2u\/NnNfgfN\/dmqKccDaYd4cXYiurj3LpjuJ3qTGn+1DO1wUPNtM6C2rbkkNQnsZSeo0ssOJrhkthlassbfH0IVEHiYGgl0nr9Xvm8VV6bTpzBMlcyCVwXthaTlc+otbg2Edy0gCYbhdrJnLAsUxjuuAO0RRtGPdA5W+TwunNX\/FkMMgrank31wDmFMrAu1ybH2TmLTAHUlnseBa4mxXXl6uHuVYydpjntVMwGu7mk0TcepbSCDGNeUnHKuH0hYFtk6D\/sVvHEMF1gTHUH9gFKs\/TsUXPYsjVOTFME4\/wfdxuuO3S7ElrRcWWscKLr1C+PEhEb5YF6rqh1E7y8idjjdppx8g6sZD1pR2OFByFBwxj+P3TZkqthXyTn8lSq2Ygqtdgg\/KDsmhoAFFPB1+TE4Y6fTV7+DElLoZUcCbl\/93woU4iyRBwM3dWK7UzdhY1G8QIgN2ptw1JnLheAIxhur53moTzQHWc8wqA40B2m1DFhuL\/OpWMPN+TKGHHrOPf7IODjABCJsai1g4uw445mStzz+2Dc4CYAWF+Zqy9YPNcjSt6OimmuSnFPalok8mQ9x8ZPzjgdlyVB2o+CCKHaLpxWiEdBkH0qfop5fO5FkiRgMehiMhTNqL5cHKIer0yh7nJVDYBXZJOFnRMxp2Z3SXfckG1hyFJBNVnwMEGIM\/Fa1IpncLi\/cvTcLeEiAdUGysf4zFFHzp1wcNTAxqLctlAgCgDdEX9rRzAGrLvbDwCRGERjDDjvjgAHiMV8kWiQAXRF\/FHOOIcYh\/LSxv75LV\/45UVKR3Ayj+dRuGksP6W1yH0ryQWaAm3MZS4AyjjoA+hyx4AEj6dOabwTYJXRUx\/UZaphJIPkXcQSKDOqjYj7NoMoBvZed7TUSyKb0CO\/+id37i6A5hdUs2OoTunjRbNcE6krnOuNkcVAOnh3tAE0LO6jZHaKg7\/ogd2doI\/\/9IaPL5qyz+3w8rOUVgvHw+P\/+7d3R+w6nCHLubMnPbY5A6iPlub+8G50CQrv1aSlpVHWATglkePgHKW0xHWnADcYD6w1+9gYcGt7PZtOVgoNXrYr4pu6ZALXxINrOrGoQF0lSl8b3x1ozQBt5jRX4n74xtP+RE+d7bYgQapDl6hTOR4NPawxeRa5HZ\/Za2CdlvzHubst9WIpVtdl+f2xjHB3S0eoJK8ZpANwhlbNKxhAjMM\/Pyj\/7xfGyaRAOBasASWPxZemVIfrifDRyuCLx6RU1yzCqRxYPALIO2uZjn5S9VyguWy1JKinSAY9E\/DJfIvCOnbQsBlZw67TDvNQjpxjsK8TCDPFy2Yt8QZwzZya2nkkPOqXmTwTWl3q6lrOHbE1N69Xi6\/PIev0XESJvuh5hOMEudcjXFjwIE3Lz\/hnZ+8W5nasLWX51mK\/L\/anV8fuq01PD0Ufum1Z\/7xmFLbk4dy5xhOLBdbtKnzi36M+2lbAdR\/kWi2LhmlxUlu5YOUr3VfTCkWxWnhHLt7TDrVpEoEUvGwG1JmSu9x3zkR3GACsXr3a+jZSr\/02ZbLWwKp9u8F6Y+DKzVRzlwsSLyNW4jDTKwE0N8B0qWgWaYcRt7dVzVeYnWyhq8FKL7RvROJdTK9TfHZv9+gUAEDQx68\/f9d7G\/o3taYU5bZYvaqqzbz3r9M37MsFgKzU7rsXrj977KGi3FZwTvnh5oFP\/ntElLPObj9Yq98Y4xzqj4WaO3wuW0eNsQdE1KS3Rx0K0BMcj67FmTg8mG578BhntbBnF+wGuyKKaK47CONp6nWSeBUaAFRbxOgOTH2kRptXt\/sXNStLWW2mVRfrOWfu1ACwEWihw\/PZQ\/tUis\/SLQw13h1OwcvgbNnHWS0zWay8pPnH1308ZnD9sbbQsi0lPh9wgI6u0PMflGelRb65YHNeVteUspoBBS24sa0dwe4o31yd1d7lBx01q8fhUTYQ\/6ne0GKe32fyTI5EN1EmAu5v\/3BwW5ByYBzv5hEDXF5SmTXwqNDTv\/QiSY3AWMOeGa9SWL166ZFwel0y4XitJ1SHEnLF\/lxrTk\/fj81U2amu95RDEnoEPd0Au80c9d2qX1tLuw0RRCYCQV\/shvN33XzJ5pRgFACy0rvbOv2RKAT8vtRQ1x1Xr1GHxj4BACzdOOjev04+2u7XdeLpoaRj1X2H3n098DqfXCmDclJPcWoeHHcfV8icPnmMvzrdWKhu02KgWghumGuV1Lsk9UEOjq9X2ZsU+2Aop3VLWlTiOXBaiMOrQcUCAFuTcl4AecFJNJU5j+ZIUYkyKO\/V0gq8UnWjSELkY67HQpQK4jgF5\/DykuZHv\/3+Ny7fkBKMWk0vym5r7fC3tIer6zJ\/8Nislz8aDnZPgAMs2zygsTUMwIHFpo08OKW8zjsJ0pqCw+xx0dvJdXWJOrWjtAPljDsOWuTtup7VZuNZ4F6Wo\/kmJhrjqla2kXmdtPdI6m0kEalk57HbVsMdUw0oXu7NOQD4GKSm8JRgtDvia+1kMRmsnJMwVdKgTQ\/PCMcGFLTmpHfGuK+xOXSoMb2lg9mvj5Dpmboexn4aADjPTosOyG\/NSu+KRH31zSmHG9LauhJ+uwAg5OOMaW4FdzMGwGIcuqOgaFg0gHMAWDhn3+1XrU0NRsWe9s7A2t0FMQ7RqK8gq+O9jcWHGtIWnLVLnOKh5yfUHk0ZkNsRCkZrmlKPtvtT\/DFcdyTGoqBPk49B0C+8MOMcotx+MkRrFhp63DsOwLuijHslJj7Ggz7s4u2QG41BxHKs+uqHMYCQbDY+I8427DpjnHVH0dpES3bk4ggvEFBhPW0EiDepp5Pk3gf2CqRcnTDu2KXiiV3pNICPwdhBx+aMPzBxaMPgomOZae1+H8Q4HG1N274\/Z+mmkjfXDGjuCCjn0iM5BP38wkkHL5tZOX7okXAoIoygo8u\/80DeW2tLX1k5uKk1IHNdGTZlq8KB2CXT9i+Yvm\/UoPpwMCqWYm2dgW1V+f9eO+D1VQNbOgN246UL4+EAf+He19NTIolHLRL11TSlrd1Z8OqqIZursjiomS3n2ekdYaTeHQdy7396asDPGQO\/n6eFO\/90+\/vvrB0sxr8rEqhvCZ038eD3F65RZ0dK8R\/vl\/\/u5TE4r2HA7\/rsxstm7gWnJ7\/6+9R+WW1fuWQruLTlSrVsaprSP\/\/ABVHukSrfedWmK2btcbfk9VVDHvj7BDkFcoHKh5W0Pn7nW4wxDhyHUbUx9p\/dUX9jc8rW\/blvrh74webCmBY8tKDCcFWum\/9JCr\/Q+wJGGYy6LnInhHI5yjymH6ndx+DCioM3XrStvLRRXQwBABRmtxZmt84Zd+Abl294bPHY\/3t\/WDSK3ATyo1OHN9z9+TVDio+CnGrbA4dD0fFD6yYMrbv5ks2PvDr+b+8PjYH3CmrumJq7Pre2f34Lk82w609PiUwpr5lcXnPLJZv\/+OKEF1cMBFAsfNTAowVZ7ehA4IrVSDLTOsv7N14zd+eStYN\/8fdJx9qD8hjGnvtg2HXn78hM7QKAf7w\/4vkPht3zhVV7DmZvrKxo7wywTJg49MiEoUesI9btKklL7Whu96\/aURgKRgI+PbGxzjtrzKHfvTQazQ4snFu58Jwdosyz75e\/9nH\/33\/to9SULq3luB5tyb2zOjsacwIdksHYAU3XzN0R9MsKxIGDCpvV9omrleysUYfTwt0MFcZRmOln785O6xhSdHT+1MqlG0vvfnxGZ7f6QL4yv04G53b9Hj3rPXp7DWx3EU+se2VlF3UnNh6LyZLcjoe\/+cEDX\/4Iq9eT7LSuBTP3pgSidoVIewz4Fy\/Y\/fC33h1afBRXUtOY\/rNnpi9eNUS0LyO1+zvXrPn5jauCIlVz1tI+Bt9YsPU3X12qqhf2Hs766VMz3l0\/QIxAfmbHT65f8YOFG33SmjgATBtR42n01r8x0OMUY3Dh5H1\/vv29zHAEr+obW0PPvV92tDXl+4+evX53\/qI73xo3uH5IcTMHqK5LFw2zTPLhV0Z\/649zOYeaptC2qnx8ajwUw0sb+2U5qQHns0bX3nH1WlFy1Y6i3zw\/ISXAxwyuxzph6D8th7YP3NlPT0cBAiz23c+tw+rFFOW2M2exIMMvY8DhrNG12Dtgx7dkzeAnl4zaWpUPLofIAOaOP3DL\/G2ep\/O+Gqdfl\/G62NYrJO8qtJ6ogH3FSLtiqV2iVJe+YwYee+irH\/TLbgeXf+3sDjz+xuj1e\/LDKdELK6rnT6ts7wz86PEZbZ3i4qo0mq9ctPO2BRsYsmxr+n\/61PSVO\/PfWlt67sTq1FBE1H\/R5KqmlvCvnhuP+3PHVZuuO2+76IpVTyTGvrvo7L01aWt29Ttn4n78mNVn5+yoaQo\/9ma58CZTyo8AMnHcnT+8WPH2+tJwMPL\/bvmgFN3yYQDlpU3fuXrDvU9XYBk8827Zv5YNvWTKwWvO2R6JBtq6eHH+sVCAb9ibP3P0IavM4o+HTht5qPpIRn1LwOrE+xv7jxtit0HUbzXDBzBtZM1rHw8AgOHFLT+\/cXnAcWHVRzJ+8PiMSAxGDWjOSuvwTChbOkJLN5a4NsOKrUVofu3V5pWzqsY5CYJojKgzL7MtHODtER86kAFARjgyfmidtsK2fR9nv39x3IHG1IsqDv7iy8vE2XFYvuKsyj++MhrJMM4lLhDpNA5HSfteYdLXwOhmHZau11UNuRcAgA\/u1\/bbry3Ny+yw96B6OcCfXh7\/1DvDrMJLNxUu3VgS8Md212TKhZNT6\/kTDn31Mxs1K2EAW\/YVrNqZB2A\/NoPzBAbw2dk7X105aFNVjrXxypn7\/8NRLyADWr61ZG9NGjDG0Lfhhbxvnr\/5jdUDDzSkAkB6SmzM4Ho0LvKknMNb6\/rvrw8DwIrtxVcX7NISuEum73108egDDWExRI0tweKB7dVHUn7190nd3SldEf\/RlpTuKFuybsBX5m\/2+3hbV+A3\/xzf0T2prcsvfOLSTf2\/dtl69F1+ZUxmjKx5bVVpXkb3r29ZlpXWZfWitTP43UWzGltDwPnkslrrQp+WJwPAqu1F9zw5zXmJrFe26VxJzs\/s+tplG+MUAgBITYlkpXe3H01RDmRs4tCGtHCX6gzsD3VHU2uawgC8f26LuwXWh9zM1uzUWFO7X92Mvukl7VNk1xBvAdxrv+SYpNtIcjhALjASFUNvkAEAzlP8\/Oc3rsjP7NBSMqvKSJT9e80AYHJ2\/72u5PXVpc5+edKctO67P7+a6e+aAAB4ZcVgK0kozmsPhyKaWfh9\/JrZe6xWFed0fNvJJ7UEeMmagVYXhhYdw9stK08JRi+bUWn1aMygpvSUbvfFHwDYX5d10BFnaV4ruKQV8PE54w5Z4csZN5hSVvfATct\/feuy\/\/r6Owtm7uIscu3cvXsPpy9ZO4gDPPLquIbWUJv1nIbjMXceSj9wJBsnn9iVTB9ZmxqM\/eKmFQMLm61xiHJ231PTdxy0vwYxuaxeS2FEJat3Fdhumsd5B429VoJvXb45O70TzyZHbeAAfl+0MLtDPxDgrDE1eNjwAO6ozo3EAIANKmphrr36eCq3mlyLOMty4qSEvU\/yIrA70gJSrIbrfsnn5uwZPbDB+UuXzZ5DubXHQk6Ed13BRnzxgh15mR1YnCLofbSl2Dp2zGDvE1WU1fkYxDjcfPHWjHA3IHlbdEV9H24ptj6PHdLA1LeYWx+mlB+B1zgATB1Rq2XOouTHOwqjnAFAapBPGHZEa4bFsKJmLRpkpEY4QOXh7N88V1GY0\/aHb76fl9m+rybzwX9M2nUw++l3hmendh9tR78DwjkH9sGm4mvPPaY1w\/rcL6flN7eunFpeI3b9ZfHYJevtDoYCfNyQIx4jCQAA63b1Q1eD1It\/iMnDGj8zY6+WX3D1M+e+kvyWjVXZ+EagD\/iMUYe1s4t\/N+\/LtTo4elCTFoGFx2lsSWtq9ymtEh6HoSO0UAzq3l4nqe\/EwmhrXVnGY2hS\/Pz6C2S+ql0dYQArtxdysUrhTinhTZ2ri6khfvXs3eClh6ra7Or6sFVs8vAjnurPyehICfJwMDp\/2j6xFzd3455+ja0Bq2sThym\/CCVV4QSTKeV1EMcKVmwvsj5MGNqQltINqvFZpIe7taP757c+8tq4jzaXfOuq9ZPL7Ks7935xxW3\/fe5jb5bPGVv77avXf+FXF3R0++UoMnhvY+nnz92Ol3TIrbAZow6Ik769buCixSNFI4YVt+ZktLtjIAOIxtgtl26LRO1dH+\/o9+zSwW4NB\/3wvc+t8TErMYVo1B\/wR7Vcw\/pQnNsOoCxK++e1Dy46qrVZsGVfPjCWl949pLhR7ZEsv3ZXP46zZf02r2tmFBknR72Q5EcpBZ7qtXcJa5VlZoyqK8hu1xytXTEAB1ixrUj8abtJQCs7xgCAMzhrdI11rwVXYpVasa3QerrAz2Di8CNac5xGMeBw9pjD4VBEW4FbZT7cXGxtDwdjowc1gDrPojkAkJkaHTmwgak1WHRFfOt22xeHZ44+HG8RebQthAcz4Ic\/vTR+4bk7Hr3zraA\/JpqXn9nx8Lfee\/qtUV+7fEMoEL127p4n3ip3TskAYN3u3Oa2cGZaJ26nNsgAsONAzk+fnhLlctasBTDumhhPn4+fM75KHLtiWz+Pueb82nN2l5U2WQdW1mRtr8qbP61SLwYAAP3zWmVnGQCwGaNq\/EwOHU4fuqNsx4FsAJhaXhfycxx7UY\/44o8Hel950fSpXm+zYwwah14mqa\/UEZqM23n3A4McgM0Zd1Bzyfj49s7ghr15AJDij736s9ez0ju1lAkAlm4s\/c6i6dNH1IJryrkdw20XUJzXUVogbzxiOz7aGuqMsMnldXFaz5dvLbEcx4jS5ozUTs6ZVgMDqDkaBoBxgxtTQ93I2cim7jyQ19Bi3eblM0fVeo0RMIB9NZlWGesEn5u9p+5o6vD+xwJIvRb9stv\/01mxf2ZG5dPvlnVH5RXErpjvoy0lF0+t9FwJg51thr+3aFZLh1\/eTeAwueyI1nJAs4NcAF+1vchxqTLEFed23nLJZmYnyfDQPysqhusVis\/FuW2K0+f8rNE1+IyYww2Z9c3BoC9mZVta86zP2\/bnv7uxWE2PRdvEtIh2MMeBi69nuKell0julxnULwzJ1AXkpCtPXNmHTBhqL0q1LMj6vLEyv7XTBwyGl7TkZNh3mAAVA4A1OwuAw7CSY+hMTtMAojG2dneB9eeU8jqR1Gn17DyQE+MwovQoKAZqF6s7mr67Js2ppBY487TF7ftzgFn5sxK+xOeV2ws5B2C8ICsyvLQBl0Hy4Bsr852rKSwnvfvLF29r6wzc89jMGaMOWc9mcPWQuqOpj74+9vVVA8cObFpfmcOFRQJ\/b2PJRVMrRXfEKtH63BXx\/eiJmfvr05ysmwHnAT+fgNYInvZs3So91JBZXR8GDviCAGNwx1Ub0sL2Nby31g5atrVgYL9mfHbRGAAoymvHgTEc5JPLa\/FKCltFbmb7E3e+m5fVWZLXonkW60P9sfCP\/3d6lDPZI9lv3CeOanV07lGyV0n2RSz7szVL2Ks5xfDFJyvzZVCU267JALNiW5FliBVlde5Rt8x99a5CAMhKb3eqVuLw3sM5x9r8wAA4nzGy1n0K65C1uwoAICu9C7wmcMOegkjU\/uL49JG1+EDM6p2FwGHqCD20Ou3hK7YXWWMyfUSNjyl2JKpqaE7bfiDTcYhw88Xb8jPb8zJhyojal5cPu2rWbmzQ0Rh75u1Rf32r\/OIp1Y99591hJY23\/\/Gc5Tv6iRIHjmQKo3SP8B9fmrhie4Fc1zAGjA0tbM3LbFVfnG9\/aO\/2f++ROV0R+35Hc1swBuKVKXadZ4+uO3+SnWO3dgT\/+4XxwFhDcxjXg\/1jv+y2kI93xWz\/PmZQU3Zahza04qj0cPfYIfL+nMa2\/Xk\/emJ6ZW26ku4pT0oKmFMGOZMkZc6CJF7EEh\/U7xsx5RkpG+W2E\/h9nLlEZZWO2dkvBw4Vw5XLQuJDY3PansPpABCN+bXDrWo3VeZyBnZ70ewAAB8MSURBVMB50M8nl9fiKRLWGY2xDzaXiFbjRZfFut35VkfSQrHxQ49gLy2cRUtHaNXOgpy0SHlpo3t4OEBrR8qWfTnW3zNG1WinAGcQlqwZEI3Zf5WXNH92zk6r2Jcv3nrbb8+7cHKVuEhe05h2\/9PTDjem\/tdXPxw3pL6tK\/B\/74zcc1ik3wwAJg6v87xgzgG6o77XVg1yuiobUlFW5\/pqpf33jv35y7blq4auhKzUYPTOz64TeehTS8Y0taakBmPHWlM5cK+XNUNGWld6ONrV5rOaPWv0Yfe1YHFULOb3+6KeUfKjLf2\/s2hmZ8Rnd1db0yn3L\/BClzl\/gitt7G2S9Cw0vhsOoPxrEfchGMY5b2oNpaXIlS0WRuOx1J0HMgFY0M\/HO5m21oD1ewq6IgwADtVnjBzQiN289e\/26jwr4Jf3P9Yvu1XN6e1\/1+4u3FeXBgB1TWkDCpqZfha+qbLAavCUEfXWU1xY5NY4vPnxoLZO\/5Sx9fi7B4D6tXFvfmunD4D7GExXcwFRVSTGnls63BoiBvwbl28KBuxnpDJTu66avefpt0be+plNDGDtrsK7H5sxr+LAg7d8GE6JvLlm0O9fHH+wIayOP5tSVqe1RJxxf212Y0vA2SQzyQp0nU8bzLW78pXrHaLtzpx+8YKdgwvlTfIvXbTphgs3ATCf+tPBeISD\/khBVmdjW9CqZuaYGjyw2B5a2kPLt5ReOGUvnmVBQU57V8SjSR6nBO1dHMJovUv3Gj17kOPEfn8w0bH\/ePYfAKDfDXeVtQ7wrAUY277ffv4JZzPctviCSAwAYHBha15mG65RJGAfW8\/fMrZ2dwFOzJx\/+S7nyYSzxx7SlkRW4RiHx98YzYEBY2t25+OGWp87uwOVtenWCv+c8Qe0ZaRFV8T\/5JKRwGBKeS2ou0TJlVb+zKCspKUgx37fjWZIr60cuqc23RqcimGNZ489gAtcMWv3im3FtU1py7aW\/OCxmd+9ZsNd16zp6Ap875HZP3ximlSvc36\/j08cfgSv7fAaZMOePK5FRM79DCrKjuDG43lZLe4Ai0secunIB\/drvWHeNtz9cCianhJNS4mEQ1F8JjzRwH0l+a0AAIzlZ3aXlza4lxVW41fvKHx\/UxGoe0XhIUVHC7O67G3aY\/bag+fWZQSuTrU4hOFxsjZ8cqAnJO\/3gRPtUkzKGSbpwt9Z398diKwPWeldPgAf8IVzdjOmXIYRNa7eWWh9fmP1wM6IPgIcYH9tJgAw4HPHH8JnETp8fdXQ5TvsWzuvrxocjcmv8FozGYlCpNsHjAV8MHf8QWw3oiV\/WTy2uj7MgE8tr9O6LQqv3F5o\/XFBRTVTTRmclPh31qshARiDmy7aJpYaVrGAP\/aV+Vt+9PjMe5+cdt+XVl44ed\/mffnXPzjvnU3FXIQRLptWVtKSndEm2qNpeMPefFTYjloD+7UXZLcAqBoDYABdEd+mvXn2KTR5APMBfOfq9eGQ\/vVJLbFCvlVSnGs3csbIGmtJhcdNzPjSzf3X7CqIxBiolmc1MuCPTRpeL6vXziGTZ7FMYmiX+hMWSYrAvb8GRqsLfaFr7eTCMpwj0IsXGAOAJWtLb7k0Y2BBCyALs\/6tKKt57sdLGIOB\/Y6CCw5w5FhapXNx+Ehz6Km3Rn\/l4s2gqistJQItwVmj6kYP0p++AIDN+\/J\/+ewkMWF7a9JeXDb86tm7cCXhUCwro7v9aMqVZ+3Ly2zXLBIA3lk38Il\/lwNjOWnd4tqyMgwA9cdSq2oz0kPR8yYeuuGCbVoiwAGa20LfffTsRucO8NDCtumjD4JLda1d\/h0Hsn99y0fTRh5+e93AHz85rSPik1MgOsY5MDalvBa4D1Br0Rn5hr0FaO1jd3dyWR2OQdhbBXzw9x\/9W5uFzu7Awp\/P64ry8ycdmjX2oLXxaFvKFvRdKIvy\/k0FWW14i2hViXMr+KzR+le4BJEY+2hLUd2xUFVt9rDiJm14LaaPrHljTYktRQ4Aruc37F4hT8dwW5iryl6lbzzIoWx0v5hKLcB5Z9R331PT\/\/CN90LBqBaXGMDgQlu67kllAOt3F3RHpeN8dPHIMYPqzxp9GNkfu+cLq7bsy7vy7N3gioofbSn50RPT2zp9jh0DMPbbF8aXD2gajx4kDPj4vdev3Hso+6rZu7SuxgBeWT7sF3+fZD0dOXFYvfV0AaieiAHkZXa++YtXAv5o0B8B0N\/TUX0k4+6\/zNp2wHkdO+fzp1X5mey1Vc+KrSU\/f2bKz760ctrIwy8vH\/bA3yq6Y8g\/CufobKkoOyIcBKAzMoDG5vT9R1LlatBxuBVldaBasfjs98UKc5yHLpxdy7eWdEUhIxy94+r1oqaH\/jnplZUDVM8D3\/3sxs+fu4OpdVqfi\/PagHMfgxmjarQpFmW278+vORoCBqt39Bta3ISlJj5MKa\/z+8B+7ZBubNgCudeiz4oroF7y61X6xu8Diy2g\/pqu+ykOR9trdufe9cjs+mNhcbSmNBz08MzZC2CnVHfUd9eis178aFiUyxhSUVZ7\/QXb0sPd2BoON6Q\/8H9Tv\/3nWcfaA9pVt7Yu37f+OPuttYPw21ymj6xZeO6OYCCGE8u9h7PvXnT2fc9UdEV9Vnemjaj1bCoH8LFYaqgr6I9yx0CsMq2dwaffGnXDg\/O2VWfK7jOY5TynJZq9dX\/uPf87\/Z7\/WDN3\/IHXVw35uVCv3SI8tgCcBxivGF7nzhes0psq86Kyh\/bzG4zbmsfl3cdid7B8axEA3DJ\/W3Gure31u\/u9\/vEAWzNWMGQAAFV1GVo94t+S3HYAGDWgOTerDZwGa+dduqnEynVX7SwUwwuqLygtONY\/D301Qt4yd0qh9YWrLcIMPm0RGD\/yAvYKznVZz1UYlPcMLttWcO0DF10zZ+8Fk6oHFjanBCOADEX7DI761+zqp5bgHd3+nz1T8eJHQz9\/zq7pI2uyM9oZAw4cOOvoDtY0pm3YU\/Dexv7LthZ2Wpmn0n6wbK6lM3D349NmfDjsmjm7ppTXZaZ1cKupnHV0BQ\/VZ6zbU\/DOutJVO\/O7Y8zOMgAYg8nldV5NVdrPOeuO+BqaU3dU5yzbWvz2uv72s1lyGcJTgnxYyVGcvlbVZn3\/0bPv\/vzaeRVV724Y8LNnJltLQZQZ4lsgAIwNK2m2nmcWaz6Qu2H93ny3Sy3N7yzKPcZPIBI43eHLt5WMKG1eeO52a0skyh56fmIUL2OdolW1mbgBuJLC3Da\/D84acwi411fJAAD40k0lVm0b9uR3RX1Bf1SYl3QoDKaW1+6vH+z8DUoU18KyBI0keL2\/trdgvfbFRYsVq\/fffPe\/9Hu8IELP8VYUuLVM\/I9nhGNZqd2+eFOJjj7YFI5x9ewoBKUEeGF2Z1ZGN+fQ2hZoaA21dvjtd+KJU+NGemX74UCsKKcjMy0SjbGWtkBjS6i1y6dfMWIMOGcM+ud2HrfZ3VFfa4e\/rcvvvH1G9YCM+Rm\/df72r1yySSQR++sy\/\/PhOd+4fNO8iqpVO4ru+POs9m6fPrCup9xSg9GCzK54zahvcb5+iAYtHIj1y+qMd4gn1Q3hrHA0K63b+jMSZYeaUlwC4AAQ8vOibO\/KOWcHGlPy0iNp8V8hVt0Q5vaKDEpzOn362\/ZsmtsDTe1B7dlM6Rw9v8kA4N7uA\/jnn687kV9mSEyPJNn7EVj4UHwTWLtLLkq6hs9rQDmw5nZfc0dYHhXvcFwzeMxTZ5Ttb0iFhlT1coWuc1cgUuiIsH11qbqTErJHiyvO+YHGsFoMDZK7cuYUQ9WGg9H7v7jq3InVovSq7cU\/fWrqrZduuaCiatO+\/O8uOqu9WxeerF+aC2\/v9u1vCHuMm\/RT0vtYHzoivv3WcHlclVQHTfaIH+3wHxUvGPToqT1BXVG2vz6sjzyy7\/rWYH1LQHbEPUfOhwNNztsOcN9lYfA4Fl8mUNy0M4\/IFycrAif71wnxgCrR1fN1B2jgtCmXf6qjycDLtjTDjdMqWV61Bs0owT33+JlC19uSOHqIhaECypof9VfzMni4GGPA7\/3Caku91r5\/fVj2+xfH\/fDaNfMmV23Zl\/+tP85ubvc7a0tX4gOajB3\/ga\/cgJc48eAok4ISKO0obOgob1fqEf0XtXnryusXrdz+jjtrEVGYec0IgCJOrR5Nz\/Yoqde0jpc4nj6SJWB1ejzdsObS4oZELg1CKMG2D+5oycu\/AigTo1in00hwuxVkzZ4zLfsiEgptpQSKAcmFg1qJbvfuRjIAGFnacsHkfdaTj1W1WX9ZPObjHQX\/9dUPJw6vW7m96PuLzmruDCiGJatCoynUq00Ed9rKvEZeeCuPKxrgMnEUzTSReIYvbcTcpsK0wmof8dDZbhQnQV5moLgwz8pxATUGaO3pRU6lgHvwi2zaol8xCPUH4BSDA1RevZhklbBFq2XjcXJp5hXcPEONp4bVvkk966aJcmYA3dZRvWr9nokDyAOdjSnBCANoaAn\/c+nwZ94unzv+8N9++GZGatc\/l5b\/5vnxXVGvdoIcFaXlrgQVXZgA3WTtDa546+6R5yhpG0VA1sdEXmyKk2yrM6KcApWXxqaaHGADc32JH7yMRHFkqIGcA2NTpk451rDP3ZPTRx\/4NpJuN5q5q4XlZ5da5OH4WFdJrR4tuHkEdpfNuWfaM4GU53I2evigeJ5b\/b5OfIeyeV\/OfU\/PWLqxZPyQhsfvemdw0dH6Y6k\/fHzWknX9udU24KoOtQYgv+nhgLyO4ugoLZwm8uBYAM6wKJmtKCjCGjqdMguui8Oenk7LLxj+7J4jUPrl7o57IgCUSJMwep0+kvUgB+i+UOpH3eipYY8KXW7YOY0C9qNKUqcUUlNGkBYTP5X1OKN7kano3Kt5Xh1TjgXHlJ2WRDh7bdXAP9\/+\/sRhdV0R\/z\/eG\/Ho4lENrc7bOYQH8TYyNcThnrpbLobCnZIAmjhtBHB+hNWrCMm1fGSovD56ng2Ls2AWvl62QpWrBu6aVaEspQ2dOibg5ex6hWRF4Pj5lZZN4ezF4+KDejg2C+ayJO5c0gBndef2I7I8gFjCua+XJPAmishd2bvQuYhdmvUqhUE9yiVIzoGxSBSefa9sW1Xu394r238k1cMKwZ0ygNdG5jHAWrzVxhZ\/0JIXcMsM1NHmuq\/U8h2GdB5vTpX643jVeLLyaJ7accbk1wz1tAuQhtFZ4lvoaSKpV6E9VzWaSan7pD2BFsbVYzWktoV1objhfZSXfaOdSuM9VSf+cNcv3b9r7YcdFkMLLSXw6r1+Y03\/N9aUAgP7EQw8MhyUPrrVi2Xjbqoo4zkOuBL5Jw5NrgW2ogGU2TI8TY4wGO6D2n63E3GXlEOhuklP0eJxkP1CHkbbhTvuPfu9QVJ\/XpTFmQZPbSj6YchQkCFw929egMsmmBIAZRmXqHDbtDnTr0DhetSO6CurONeu8CF6vNKsCn03Cwc0ph4izoUDsoj52kVdcI2YaLmo3+1ttQJ4NrmiTpTDq8da1WruTxekOmb6vGu4gjlXt4tTawscrW1yBpD4PUdAONYk0fsC1kxWlZz0mqK4Op1ivKQ2vArLo5w4ho3YKsDVPwHvZ0phuYsrlqrbq6tz7owXi4eJmxxe6C6Dy\/LCiBWH5fJcwBSdADJZ0XclsKPR0AKUHrJc1o9LgrB7MShMJsw4K1YKOxFPrnS03\/h09Q5Q38VRWpeFtbgHVlMyx43Hw4sVjibanYwkgz6QQgPyeR7ZLP4ZWDUmu6uSludom6m5IoASteSfaKmjhMrEt2S15aV1BUjdiNM3oUAtOZc1a4mZ0wVQzc49DszpiLtaCVPsG8NUqWsdxHk+PlyfBa0GfDlDaNipRPeA6uFiXrAjlcEZqV1slIrSUh4vo1IOAb280kjPpYFsoGozSSCJAkbeVwQ9rs6iZZfeYU3907ZgqRXFSrgr1Ogu2X1dShOJU7OmWz3jdVmP6KwMJglSDO1EII1eKe\/EYXkitZEAul2KYh7vuvJqhjRZjipHnoJz0V00iY5Uld64XKQnCTSgu8g42QF2Xjit9fD7HPkUNSCLPipG6NFcVwPiJ1OnkyS+kcMZVu7eJfbHGRHurAO5Whv22AyctA1Zs\/hXZMK6n+Z6MS0BU0Koyxwto7en07Fo4bxlWWRSip0xaU+iDaCapoiK2BlpyQV3DNTtrTyG1DPDdJUCLTdBKrD3Ijdhp694ALH708YTXB1BnxWfi7ujrUTU9ruTqXjJCD6Q4WsrqjPS8m1wnTEZ6oXeFLD1vp+FCxcCOIaoSQicP90ZC+c9GzJRnIMsqZ3Oe92onQIZKG4MTob1UzvZu540AlrgoVPEa487N+P4To\/qeqSJY2NFhq7bn1OYc6UquRfsvRzUY53AxUTmIsSmPuMhnZFaL0ejpHWf4WFx1K55WDkmSPPuMVSOYnrHufOQpttx4CmzJtE9ZfjsSlSH1R+vTvzeuBN5e1yP6PUILJMuz\/yNK3MmDmDOtVMN4eDdgyJPgaYEUPT2zJzt8KbGdoYctjAgPX9WvYzmYkSGdZzFkjom3Cs26uBOaSOEl9zgZCWgd42rNeABxy5GCeZMsWBdY7h1XA6gVbdMUpwCHL3cX25HA4IbpnkizVRwszXviUbFdZQz6XgAmeuRaXyINCFcbxLobQFzYUPu1NS2NqU40gBype5Z1AxRWL88Ci1ZlTQJO2+XZ7FDOVdsXSkMqmhRMMTt4ahmrfHetqhqA8cH3Z7UuKTkk3iVzuSFBrmRK3\/a51J7l9jjuF2tvMIkZOkII16mo82I2C5zBNFT93UH3GXHfWgZgWialsRxx7+IY12Nk1mAx37Vck5pXD1xevsilgxJOBpouaJ2wUNam3Y\/FuzPeEbdmaosA6g2Fc2VuDMlUE1cOamQMZPmq1mY6BfHBgd6Sa4qSinjeDccFmQx7Olwj1SLx7rlzg02pddeFSqOEssbTZMVP5WJiH+TjIM++\/IUagzEPRKfRAv1iXB5QzFBDOQE4UbJU6uBgTmns1vonJqjVYz3uXqbU\/lGjhN5C0Faem44Y4AckeMTxwhO+NiXX3opQYnLLr88wd7ExyYmcc2JSVabE3Pmnfck5oi\/\/NLL+jYGE8eUpKeFvMqrBRMqpUeS7G0B9z6JO3gKh7JHNScmWW1OzJl33l578U2PztujmpP6KCVBECcHCZggDIYETBAGQwImCIPp2W2kZF3GOBlOps0nc+zJ1Hwy9M05StaFqGTNUa\/NAkVggjAYEjBBGAwJmCAMhgRMEAZDAiYIgyEBE4TBkIAJwmBIwARhMCRggjCYvvJ1QhOfEOqb\/f209Sgxyfqy4clAXyckiE8LJGCCMBgSMEEYDAmYIAyGBEwQBkMCJgiDIQEThMGQgAnCYEjABGEwfeWdWCbWfAa8UekU1pysJ8ASc+Y9W6ZBEZggDIYETBAGQwImCIMhAROEwZCACcJgSMAEYTAkYIIwGBIwQRgMCZggDOZUvhPrzCNZv2yYmNP33FKynpdKTN98IipZs69BEZggDIYETBAGQwImCIMhAROEwZCACcJgSMAEYTAkYIIwGBIwQRgMCZggDOZUvhPLRD5tD6L1zV8n7JvvD+ubvyCpQRGYIAyGBEwQBkMCJgiDIQEThMGQgAnCYEjABGEwJGCCMBgSMEEYDAmYIAymZ09iJaZvPtV05j091jcx8RcVT4Y+YlcUgQnCYEjABGEwJGCCMBgSMEEYDAmYIAyGBEwQBkMCJgiDIQEThMGQgAnCYE7lk1iJSdZv6p0+zrxf66Nn6U78vH1krCgCE4TBkIAJwmBIwARhMCRggjAYEjBBGAwJmCAMhgRMEAZDAiYIgyEBE4TB9N6TWCZyMr\/ll6xf6zPiN\/V6RLJ+UbGPvPUqMRSBCcJgSMAEYTAkYIIwGBIwQRgMCZggDIYETBAGQwImCIMhAROEwZCACcJg6EmsRPTNt14lblXffPfYybTqZJ4AO+OfaaMITBAGQwImCIMhAROEwZCACcJgSMAEYTAkYIIwGBIwQRgMCZggDIYETBAG03tPYvWRX3M7hSTrjVknw+l7bun0PS\/VN5+I6iPzSxGYIAyGBEwQBkMCJgiDIQEThMGQgAnCYEjABGEwJGCCMBgSMEEYDAmYIAzmVD6JZcSvuZ1Czrz+9s1nj0w8b6\/ZBkVggjAYEjBBGAwJmCAMhgRMEAZDAiYIgyEBE4TBkIAJwmBIwARhMCRggjAYdua9qoogPj1QBCYIgyEBE4TBkIAJwmBIwARhMCRggjAYEjBBGAwJmCAMhgRMEAZDAiYIgyEBE4TBkIAJwmBIwARhMCRggjAYErAXM2YAY\/Dqq\/r27m4oKYGUFNi3DwAgNxcYg9ZWjxq+9jW9hqFDgTE4cCDRea0y1n9+P5SUwJQp8P3v26dLUFW8yq+4AhiDH\/\/Y41zTpgFjcPHFidqDqauDO+6AigrIzISSErjsMnjjjbiFE1eOu8kYZGfD6NFwww2wapV3ycSD9imHE25eeIED8PPP17c\/9hgH4DfdZP+Zk8MBeEuLRw233cYB+CuvyC1DhnAAXl2d6LxWmeuu4zffzG+8kV96KR8wgAPwUIi\/+26iqjwrv+ceDsAvvdTjRJWVHIAXFPBAgB85kqhJFps22Z0tLOSzZvH+\/TkAB+C33srb2npcOe7mzTfzq6\/mY8bYFT72mEfJxIP26YYEHIdx4zgAX7NG3+jz8R077D9Pk4BxmUiE\/+EPth6EVE5EwM8+ywH4iBG8qcnjRA8+yAH4okX2v8fFEtgDD\/BIxN6yZw9fsIDPnMk7OnpcuedQvPYaD4V4KHR8x0QgSMBxeOYZDsCvv15uWbyYA\/Brr5VbekHAFuefzwH4smVxi2lb1q3jaWk8K4tv2eJ9ounT+ZgxvKuLZ2Xx+fMTNYk7EbWszGOXO\/yeSOXxunnddRyAP\/\/88UsSDrQGjsPChVBWBs8+KxdgDz0EPh\/88IdJaMyECQAAmzadUOH6erjySujogCefhNGjPQrs2wcrV8Kll0IwCBddBEuWQGNjogqbmgAAYjGPXampJ1s5ZtgwAIA9e060PEEXseLi98P3vgddXfDwwwAAGzfCm2\/CggUwfnwSGlNbCwAwYMDxS0ajcM01UFkJ99wDV1zhXea55wAALr0UAGDBAohE4IUXEtU5Zgzk5MCePfDTn0I0epwG9LRyzIYNAABDhpxoeYIEnIgbb4QBA+CRR6C9HX77WwBITvitqYE33wQAmDTp+IVvvx3efRcAYO7cuGWefRYyMmD2bACA+fPB54Nnn01UZzAIDz8MPh\/cey+MGQN\/\/St0dp6yygV\/+Qu89BIUFMC8eSdUnrBIdg7ft\/ntbzkAv+8+Hg7zefP0vad1DRyJ8Opq\/txz9uW0O+9MVJW15Sc\/sS93AfAJE+QFJ0xVFQfgCxfKLdOn81CINzQkahjnfPFiPmqUfa24sJDfc4\/HISdYudXa66\/nt93Gb7uNX301LyvjADwtjb\/0UtwBIbwgASekrY0XFtpW+\/bb+t7TJGDtv1CIf\/3rihrjCRiAZ2XxTZvsi16PPOJxil\/\/mgPwZ56RW+6\/3+P+TTxeeMGuHIDn5Oh6O8HKPbv59a\/zbdu8B4QEHJ9T+QPfZyCpqfDNb8JPfgLTp8N55+l7AwEAgI4OSE\/Xd3V0yAI95brrIC0NfD4oLoYhQ2DePBg48IQO9PngmWdg7Fh46CGYPBnuuQcWLoTsbKWMtUZdvBiWLbO3VFfb27\/85eOf4oor4IorYNUquOsueP99uPpqWLcOxo79JJVXV0NpKQDAlCmwZg3MnQsjR55QNwlMsj1In+dvf9PvJwmsxG\/DBo9dVphauVJuOZnbSMctZm355S\/llptu4gD8rruUA6uquM\/nEf2sOH\/cLFrj+us5AL\/tth5XrrV\/yRIOwIcM8bilTBH4eNBFrJNgxAgAgF27PHZZG8vKerU9118vP99\/P2RkwO9+B7t3y43PPQexGPzhD8C58t+dd0JXF7z00ic5nej+J678ggvgoougshJ+97ueNYCgq9AnxbnnAoB9nwnz8stQVQWTJkFubq+3yaGkxL4NdtddcqN1QXjBAr2wtSXe5eK6OvjrXz22V1UBOF7sE1du8eCD4PPBAw9AfX2iYoSbZKcAfZ4EKfSRIzwriwPwe++VF5mWLeODBnEA\/sQTSuFeSKG1A9va7EeprctvVoo7YYJHhdZTU6GQ93OX8+dzAH7llbyyUm5cvpwXF3Of75NU7tlaKyG\/\/fbj9JRQoQh8EuTnw1NPQU4O3HsvFBfDnDkwciTMng1VVXDrrfClL3kccuut8LnPKf95FjslpKbC\/fcDAHz72wBOinv55R4lg0GYPx+6urwfuli0CObNgxdegCFDYOxYOO88GDkSZs6E2lq47z772t4nrlxw\/\/0QDsP\/\/A\/s3NnDfn66SbYH6fMkiMAWBw\/ym27iEybwtDQ+ZAifP5+\/+aZHMc97J9bNGK3MqYrAFpMn27eUZs3Sr6thnnySA\/AFC+Ke9Ikn+Pz5vLiYh8N81Ci+cCH\/+GO5t0eVx2vtnXfaof5E+kVwzjmnXyckCIOhFJogDIYETBAGQwImCIMhAROEwZCACcJgSMAEYTAkYIIwGBIwQRgMCZggDOb\/A+xzFRtiL\/3HAAAAAElFTkSuQmCC\n<\/pre><\/dd><\/dl><dl><dt><span class=\"kint-access-path-trigger\" title=\"Show access path\">&rlarr;<\/span><dfn>foto<\/dfn> =&gt; <var>string<\/var> (0) \"\"<div class=\"access-path\">$value['foto']<\/div><\/dt><\/dl><dl><dt><span class=\"kint-access-path-trigger\" title=\"Show access path\">&rlarr;<\/span><dfn>nik<\/dfn> =&gt; <var>string<\/var> (16) \"1371041108920004\"<div class=\"access-path\">$value['nik']<\/div><\/dt><\/dl><dl><dt><span class=\"kint-access-path-trigger\" title=\"Show access path\">&rlarr;<\/span><dfn>id_jabatan<\/dfn> =&gt; <var>string<\/var> (1) \"1\"<div class=\"access-path\">$value['id_jabatan']<\/div><\/dt><\/dl><dl><dt><span class=\"kint-access-path-trigger\" title=\"Show access path\">&rlarr;<\/span><dfn>id_divisi<\/dfn> =&gt; <var>string<\/var> (1) \"1\"<div class=\"access-path\">$value['id_divisi']<\/div><\/dt><\/dl><\/dd><\/dl><\/div>","jabatan":"<div class=\"kint-rich\"><dl><dt class=\"kint-parent\"><span class=\"kint-popup-trigger\" title=\"Open in new window\">&boxbox;<\/span><span class=\"kint-search-trigger\" title=\"Show search box\">&telrec;<\/span><input type=\"text\" class=\"kint-search\" value=\"\"><nav><\/nav><dfn>$value<\/dfn> <var>array<\/var> (4)<\/dt><dd><ul class=\"kint-tabs\"><li class=\"kint-active-tab\">Table (4)<\/li><li>Contents (4)<\/li><\/ul><ul class=\"kint-tab-contents\"><li class=\"kint-show\"><pre><table><thead><tr><th><\/th><th>id_jabatan<\/th><th>nama_jabatan<\/th><\/tr><\/thead><tbody><tr><th>0<\/th><td title=\"string (1)\">1<\/td><td title=\"string (8)\">Operator<\/td><\/tr><tr><th>1<\/th><td title=\"string (1)\">2<\/td><td title=\"string (6)\">Leader<\/td><\/tr><tr><th>2<\/th><td title=\"string (1)\">4<\/td><td title=\"string (10)\">Supervisor<\/td><\/tr><tr><th>3<\/th><td title=\"string (1)\">3<\/td><td title=\"string (7)\">Foreman<\/td><\/tr><\/tbody><\/table><\/pre><\/li><li><dl><dt class=\"kint-parent\"><span class=\"kint-access-path-trigger\" title=\"Show access path\">&rlarr;<\/span><span class=\"kint-popup-trigger\" title=\"Open in new window\">&boxbox;<\/span><nav><\/nav><dfn>0<\/dfn> =&gt; <var>array<\/var> (2)<div class=\"access-path\">$value[0]<\/div><\/dt><dd><dl><dt><span class=\"kint-access-path-trigger\" title=\"Show access path\">&rlarr;<\/span><dfn>id_jabatan<\/dfn> =&gt; <var>string<\/var> (1) \"1\"<div class=\"access-path\">$value[0]['id_jabatan']<\/div><\/dt><\/dl><dl><dt><span class=\"kint-access-path-trigger\" title=\"Show access path\">&rlarr;<\/span><dfn>nama_jabatan<\/dfn> =&gt; <var>string<\/var> (8) \"Operator\"<div class=\"access-path\">$value[0]['nama_jabatan']<\/div><\/dt><\/dl><\/dd><\/dl><dl><dt class=\"kint-parent\"><span class=\"kint-access-path-trigger\" title=\"Show access path\">&rlarr;<\/span><span class=\"kint-popup-trigger\" title=\"Open in new window\">&boxbox;<\/span><nav><\/nav><dfn>1<\/dfn> =&gt; <var>array<\/var> (2)<div class=\"access-path\">$value[1]<\/div><\/dt><dd><dl><dt><span class=\"kint-access-path-trigger\" title=\"Show access path\">&rlarr;<\/span><dfn>id_jabatan<\/dfn> =&gt; <var>string<\/var> (1) \"2\"<div class=\"access-path\">$value[1]['id_jabatan']<\/div><\/dt><\/dl><dl><dt><span class=\"kint-access-path-trigger\" title=\"Show access path\">&rlarr;<\/span><dfn>nama_jabatan<\/dfn> =&gt; <var>string<\/var> (6) \"Leader\"<div class=\"access-path\">$value[1]['nama_jabatan']<\/div><\/dt><\/dl><\/dd><\/dl><dl><dt class=\"kint-parent\"><span class=\"kint-access-path-trigger\" title=\"Show access path\">&rlarr;<\/span><span class=\"kint-popup-trigger\" title=\"Open in new window\">&boxbox;<\/span><nav><\/nav><dfn>2<\/dfn> =&gt; <var>array<\/var> (2)<div class=\"access-path\">$value[2]<\/div><\/dt><dd><dl><dt><span class=\"kint-access-path-trigger\" title=\"Show access path\">&rlarr;<\/span><dfn>id_jabatan<\/dfn> =&gt; <var>string<\/var> (1) \"4\"<div class=\"access-path\">$value[2]['id_jabatan']<\/div><\/dt><\/dl><dl><dt><span class=\"kint-access-path-trigger\" title=\"Show access path\">&rlarr;<\/span><dfn>nama_jabatan<\/dfn> =&gt; <var>string<\/var> (10) \"Supervisor\"<div class=\"access-path\">$value[2]['nama_jabatan']<\/div><\/dt><\/dl><\/dd><\/dl><dl><dt class=\"kint-parent\"><span class=\"kint-access-path-trigger\" title=\"Show access path\">&rlarr;<\/span><span class=\"kint-popup-trigger\" title=\"Open in new window\">&boxbox;<\/span><nav><\/nav><dfn>3<\/dfn> =&gt; <var>array<\/var> (2)<div class=\"access-path\">$value[3]<\/div><\/dt><dd><dl><dt><span class=\"kint-access-path-trigger\" title=\"Show access path\">&rlarr;<\/span><dfn>id_jabatan<\/dfn> =&gt; <var>string<\/var> (1) \"3\"<div class=\"access-path\">$value[3]['id_jabatan']<\/div><\/dt><\/dl><dl><dt><span class=\"kint-access-path-trigger\" title=\"Show access path\">&rlarr;<\/span><dfn>nama_jabatan<\/dfn> =&gt; <var>string<\/var> (7) \"Foreman\"<div class=\"access-path\">$value[3]['nama_jabatan']<\/div><\/dt><\/dl><\/dd><\/dl><\/li><\/ul><\/dd><\/dl><\/div>","divisi":"<div class=\"kint-rich\"><dl><dt class=\"kint-parent\"><span class=\"kint-popup-trigger\" title=\"Open in new window\">&boxbox;<\/span><span class=\"kint-search-trigger\" title=\"Show search box\">&telrec;<\/span><input type=\"text\" class=\"kint-search\" value=\"\"><nav><\/nav><dfn>$value<\/dfn> <var>array<\/var> (2)<\/dt><dd><ul class=\"kint-tabs\"><li class=\"kint-active-tab\">Table (2)<\/li><li>Contents (2)<\/li><\/ul><ul class=\"kint-tab-contents\"><li class=\"kint-show\"><pre><table><thead><tr><th><\/th><th>id_divisi<\/th><th>nama_divisi<\/th><\/tr><\/thead><tbody><tr><th>0<\/th><td title=\"string (1)\">1<\/td><td title=\"string (23)\">Departement Engineering<\/td><\/tr><tr><th>1<\/th><td title=\"string (1)\">2<\/td><td title=\"string (15)\">Departement HRD<\/td><\/tr><\/tbody><\/table><\/pre><\/li><li><dl><dt class=\"kint-parent\"><span class=\"kint-access-path-trigger\" title=\"Show access path\">&rlarr;<\/span><span class=\"kint-popup-trigger\" title=\"Open in new window\">&boxbox;<\/span><nav><\/nav><dfn>0<\/dfn> =&gt; <var>array<\/var> (2)<div class=\"access-path\">$value[0]<\/div><\/dt><dd><dl><dt><span class=\"kint-access-path-trigger\" title=\"Show access path\">&rlarr;<\/span><dfn>id_divisi<\/dfn> =&gt; <var>string<\/var> (1) \"1\"<div class=\"access-path\">$value[0]['id_divisi']<\/div><\/dt><\/dl><dl><dt><span class=\"kint-access-path-trigger\" title=\"Show access path\">&rlarr;<\/span><dfn>nama_divisi<\/dfn> =&gt; <var>string<\/var> (23) \"Departement Engineering\"<div class=\"access-path\">$value[0]['nama_divisi']<\/div><\/dt><\/dl><\/dd><\/dl><dl><dt class=\"kint-parent\"><span class=\"kint-access-path-trigger\" title=\"Show access path\">&rlarr;<\/span><span class=\"kint-popup-trigger\" title=\"Open in new window\">&boxbox;<\/span><nav><\/nav><dfn>1<\/dfn> =&gt; <var>array<\/var> (2)<div class=\"access-path\">$value[1]<\/div><\/dt><dd><dl><dt><span class=\"kint-access-path-trigger\" title=\"Show access path\">&rlarr;<\/span><dfn>id_divisi<\/dfn> =&gt; <var>string<\/var> (1) \"2\"<div class=\"access-path\">$value[1]['id_divisi']<\/div><\/dt><\/dl><dl><dt><span class=\"kint-access-path-trigger\" title=\"Show access path\">&rlarr;<\/span><dfn>nama_divisi<\/dfn> =&gt; <var>string<\/var> (15) \"Departement HRD\"<div class=\"access-path\">$value[1]['nama_divisi']<\/div><\/dt><\/dl><\/dd><\/dl><\/li><\/ul><\/dd><\/dl><\/div>"}},"session":{"__ci_last_regenerate":"<pre>1694927005<\/pre>","_ci_previous_url":"http:\/\/localhost:8080\/daftar_karyawan","logged_in":"1"},"headers":{"Host":"localhost:8080","Connection":"keep-alive","Sec-Ch-Ua":"&quot;Chromium&quot;;v=&quot;116&quot;, &quot;Not)A;Brand&quot;;v=&quot;24&quot;, &quot;Google Chrome&quot;;v=&quot;116&quot;","Sec-Ch-Ua-Mobile":"?0","Sec-Ch-Ua-Platform":"&quot;Windows&quot;","Upgrade-Insecure-Requests":"1","Dnt":"1","User-Agent":"Mozilla\/5.0 (Windows NT 10.0; Win64; x64) AppleWebKit\/537.36 (KHTML, like Gecko) Chrome\/116.0.0.0 Safari\/537.36","Accept":"text\/html,application\/xhtml+xml,application\/xml;q=0.9,image\/avif,image\/webp,image\/apng,*\/*;q=0.8,application\/signed-exchange;v=b3;q=0.7","Sec-Fetch-Site":"same-origin","Sec-Fetch-Mode":"navigate","Sec-Fetch-User":"?1","Sec-Fetch-Dest":"document","Referer":"http:\/\/localhost:8080\/daftar_karyawan","Accept-Encoding":"gzip, deflate, br","Accept-Language":"ms-MY,ms;q=0.9,en-US;q=0.8,en;q=0.7,id;q=0.6","Cookie":"_ga=GA1.1.1496938251.1694386290; killme=dont; penugasan=oke; _gid=GA1.1.1696991708.1694886050; csrf_cookie_name=ed2bac2db34bd12b98ddb6475c1ae779; ci_session=f3vl7tbnl51jo60klb9pdh52t2fu9f9d"},"cookies":{"_ga":"GA1.1.1496938251.1694386290","killme":"dont","penugasan":"oke","_gid":"GA1.1.1696991708.1694886050","csrf_cookie_name":"ed2bac2db34bd12b98ddb6475c1ae779","ci_session":"f3vl7tbnl51jo60klb9pdh52t2fu9f9d"},"request":"HTTP\/1.1","response":{"statusCode":200,"reason":"OK","contentType":"text\/html; charset=UTF-8","headers":{"Cache-Control":"no-store, max-age=0, no-cache","Content-Type":"text\/html; charset=UTF-8"}}},"config":{"ciVersion":"4.3.7","phpVersion":"8.2.0","phpSAPI":"cli-server","environment":"development","baseURL":"http:\/\/localhost:8080","timezone":"UTC","locale":"en","cspEnabled":false}}